Workbook

Sheet 05_Dashboard
A1: PHOTO LAB — Master Timeline v0.20
A2: KPI | B2: Значение | C2: Комментарий
A3: Всего исторических узлов | B3: =COUNTA('01_Master_Facts'!$A$2:$A$800) | C3: Количество строк в 01_Master_Facts
A4: Узлов с важностью 5 | B4: =COUNTIF('01_Master_Facts'!$N$2:$N$800,5) | C4: Критические для карты и уроков
A5: Узлов для PL-001–PL-041 | B5: =SUM(E10:E55) | C5: Узлы для заполненных PL; PL-040 пока планируется и даёт 0 узлов
A6: Строк с пометкой «проверить позже» | B6: =COUNTA('01_Master_Facts'!$W$2:$W$800) | C6: Живая формула: считает непустые ячейки в «Проверить позже»
A9: Ветка развития | B9: Количество узлов | D9: Урок | E9: Количество узлов
A10: Оптика / камера-обскура | B10: =COUNTIF('01_Master_Facts'!$H$2:$H$800,A10) | D10: PL-001 | E10: =COUNTIF('01_Master_Facts'!$O$2:$O$800,D10)
A11: Оптические инструменты | B11: =COUNTIF('01_Master_Facts'!$H$2:$H$800,A11) | D11: PL-002 | E11: =COUNTIF('01_Master_Facts'!$O$2:$O$800,D11)
A12: Фотохимия | B12: =COUNTIF('01_Master_Facts'!$H$2:$H$800,A12) | D12: PL-003 | E12: =COUNTIF('01_Master_Facts'!$O$2:$O$800,D12)
A13: Гелиография | B13: =COUNTIF('01_Master_Facts'!$H$2:$H$800,A13) | D13: PL-004 | E13: =COUNTIF('01_Master_Facts'!$O$2:$O$800,D13)
A14: Дагеротип | B14: =COUNTIF('01_Master_Facts'!$H$2:$H$800,A14) | D14: PL-005 | E14: =COUNTIF('01_Master_Facts'!$O$2:$O$800,D14)
A15: Фотогенный рисунок / фотограмма | B15: =COUNTIF('01_Master_Facts'!$H$2:$H$800,A15) | D15: PL-006 | E15: =COUNTIF('01_Master_Facts'!$O$2:$O$800,D15)
A16: Негатив-позитив | B16: =COUNTIF('01_Master_Facts'!$H$2:$H$800,A16) | D16: PL-007 | E16: =COUNTIF('01_Master_Facts'!$O$2:$O$800,D16)
A17: Печать / тиражирование | B17: =COUNTIF('01_Master_Facts'!$H$2:$H$800,A17) | D17: PL-008 | E17: =COUNTIF('01_Master_Facts'!$O$2:$O$800,D17)
A18: Уникальный позитив | B18: =COUNTIF('01_Master_Facts'!$H$2:$H$800,A18) | D18: PL-009 | E18: =COUNTIF('01_Master_Facts'!$O$2:$O$800,D18)
A19: Цвет | B19: =COUNTIF('01_Master_Facts'!$H$2:$H$800,A19) | D19: PL-010 | E19: =COUNTIF('01_Master_Facts'!$O$2:$O$800,D19)
A20: Проекция / распространение | B20: =COUNTIF('01_Master_Facts'!$H$2:$H$800,A20) | D20: PL-011 | E20: =COUNTIF('01_Master_Facts'!$O$2:$O$800,D20)
A21: Цвет | B21: =COUNTIF('01_Master_Facts'!$H$2:$H$600,A21) | D21: PL-012 | E21: =COUNTIF('01_Master_Facts'!$O$2:$O$800,D21)
A22: Проекция / распространение | B22: =COUNTIF('01_Master_Facts'!$H$2:$H$600,A22) | D22: PL-013 | E22: =COUNTIF('01_Master_Facts'!$O$2:$O$800,D22)
D23: PL-014 | E23: =COUNTIF('01_Master_Facts'!$O$2:$O$800,D23)
D24: PL-015 | E24: =COUNTIF('01_Master_Facts'!$O$2:$O$800,D24)
D25: PL-016 | E25: =COUNTIF('01_Master_Facts'!$O$2:$O$800,D25)
D26: PL-017 | E26: =COUNTIF('01_Master_Facts'!$O$2:$O$800,D26)
D27: PL-018 | E27: =COUNTIF('01_Master_Facts'!$O$2:$O$800,D27)
D28: PL-019 | E28: =COUNTIF('01_Master_Facts'!$O$2:$O$800,D28)
D29: PL-020 | E29: =COUNTIF('01_Master_Facts'!$O$2:$O$800,D29)
D30: PL-021 | E30: =COUNTIF('01_Master_Facts'!$O$2:$O$800,D30)
D31: PL-022 | E31: =COUNTIF('01_Master_Facts'!$O$2:$O$800,D31)
D32: PL-023 | E32: =COUNTIF('01_Master_Facts'!$O$2:$O$800,D32)
D33: PL-024 | E33: =COUNTIF('01_Master_Facts'!$O$2:$O$800,D33)
D34: PL-025 | E34: =COUNTIF('01_Master_Facts'!$O$2:$O$800,D34)
... D54: PL-045 | E54: =COUNTIF('01_Master_Facts'!$O$2:$O$800,D54)
A55: Фундаментальная предпосылка | B55: =COUNTIF('01_Master_Facts'!$Z$2:$Z$800,"Фундаментальная предпосылка") | D55: PL-046 | E55: =COUNTIF('01_Master_Facts'!$O$2:$O$800,D55)
A56: Технология / процесс | B56: =COUNTIF('01_Master_Facts'!$Z$2:$Z$800,"Технология / процесс") | D56: будущие PL | E56: =COUNTIF('01_Master_Facts'!$O$2:$O$800,D56)
A57: Инструмент / устройство | B57: =COUNTIF('01_Master_Facts'!$Z$2:$Z$800,"Инструмент / устройство") | D57: межурочный узел | E57: =COUNTIF('01_Master_Facts'!$O$2:$O$800,D57)
A58: Публикация / объявление | B58: =COUNTIF('01_Master_Facts'!$Z$2:$Z$800,"Публикация / объявление")
A59: Терминология / язык | B59: =COUNTIF('01_Master_Facts'!$Z$2:$Z$800,"Терминология / язык")
A60: Связь / переход | B60: =COUNTIF('01_Master_Facts'!$Z$2:$Z$800,"Связь / переход")
A61: Тиражирование / публикация | B61: =COUNTIF('01_Master_Facts'!$Z$2:$Z$800,"Тиражирование / публикация")
A62: Распространение / коммерциализация | B62: =COUNTIF('01_Master_Facts'!$Z$2:$Z$800,"Распространение / коммерциализация")
A63: Научное применение / пример | B63: =COUNTIF('01_Master_Facts'!$Z$2:$Z$800,"Научное применение / пример")
A64: Применение / жанр | B64: =COUNTIF('01_Master_Facts'!$Z$2:$Z$800,"Применение / жанр")
A65: Ключевой исторический узел | B65: =COUNTIF('01_Master_Facts'!$Z$2:$Z$800,"Ключевой исторический узел")

Sheet 01_Master_Facts
A1: ID | B1: Период / дата | C1: Точность даты | D1: Страна | E1: Город / регион | F1: Персона / группа | G1: Событие | H1: Ветка развития | I1: Технология / процесс | J1: Что изменилось | K1: Предыдущая связь | L1: Следующая связь | M1: Статус ветки | N1: Важность 1–5 | O1: Привязка к уроку | P1: Источник ID | Q1: Название источника | R1: URL источника | S1: Уверенность 1–5 | T1: Комментарий для лекции | U1: Визуальная идея для карты | V1: Теги | W1: Проверить позже | X1: Координаты (lat, lon) | Y1: Подветка (детали) | Z1: Тип узла | AA1: Флагман урока (да/нет)
A2: PL-HIST-0001 | B2: ок. 1011–1021 | C2: диапазон | D2: Египет / исламский научный мир | E2: Каир / Басра (контекст учёного) | F2: Ибн аль-Хайсам (Альхазен) | G2: В «Книге оптики» системно исследует свет, зрение и опыт тёмной комнаты с малым отверстием. | H2: Оптика / камера-обскура | I2: Камера-обскура / pinhole image | J2: Фотографии ещё нет, но появляется научная база: свет распространяется прямыми линиями и может строить изображение. | K2: Античная оптика и астрономические наблюдения | L2: Европейская оптика, камера-обскура как инструмент наблюдения | M2: Оптическая предпосылка | N2: 5 | O2: PL-001 | P2: SRC-001 | Q2: AramcoWorld — Ibn al-Haytham: Testing is Believing | R2: https://www.aramcoworld.com/en/articles/2023/ibn-al-haytham-testing-is-believing | S2: 4 | T2: Важно сказать аккуратно: он не изобрёл фотографию, а дал фундамент для понимания изображения светом. | U2: Стартовая точка карты: луч света входит в тёмную комнату и строит перевёрнутое изображение. | V2: #оптика #камера-обскура #ИбнАльХайсам #PL001 | W2: Уточнить формулировку места: не привязывать к современной стране слишком жёстко. | X2: 30.0444, 31.2357 | Z2: Фундаментальная предпосылка | AA2: да
A3: PL-HIST-0002 | B3: 1545 | C3: год | D3: Нидерланды / Священная Римская империя | E3: Лёвен / Фрисландия (контекст публикации) | F3: Гемма Фризиус | G3: Публикует один из ранних известных рисунков камеры-обскуры, использованной для наблюдения солнечного затмения. | H3: Оптика / камера-обскура | I3: Камера-обскура как астрономический инструмент | J3: Принцип тёмной комнаты становится не только философским описанием, но и изображаемым инструментом наблюдения. | K3: Ибн аль-Хайсам и средневековая оптика | L3: Линза и художественное применение камеры-обскуры | M3: Оптическая предпосылка | N3: 3 | O3: PL-001 | P3: SRC-003 | Q3: Max Planck Institute — Camera Obscura PDF | R3: https://www.mpiwg-berlin.mpg.de/sites/default/files/Preprints/P307.pdf | S3: 3 | T3: Можно использовать как промежуточный узел: камера-обскура служит не фотографии, а безопасному наблюдению солнца. | U3: Иконка солнечного затмения + тёмная комната. | V3: #оптика #астрономия #камера-обскура | W3: Нужен первичный источник/точная ссылка на публикацию Frisius. | X3: 50.8798, 4.7005 | Z3: Инструмент / устройство
A4: PL-HIST-0003 | B4: 1550 | C4: год | D4: Италия | E4: Павия / Италия | F4: Джероламо Кардано | G4: Описывает использование стеклянной линзы в камере-обскуре для улучшения изображения. | H4: Оптика / камера-обскура | I4: Линза в камере-обскуре | J4: Камера-обскура становится ближе к будущей камере: не просто отверстие, а оптическое формирование более яркого и резкого изображения. | K4: Пинхол / тёмная комната | L4: Della Porta и популяризация камеры-обскуры | M4: Оптическая предпосылка | N4: 4 | O4: PL-001 | P4: SRC-002 | Q4: IMSS / Museo Galileo — Camera Obscura | R4: https://redi.imss.fi.it/inventions/index.php/Camera_Obscura | S4: 4 | T4: Для новичка: отверстие даёт картинку, линза делает её ярче и удобнее. | U4: На линии добавить маленькую линзу перед тёмной комнатой. | V4: #оптика #линза #камера | X4: 45.1847, 9.1582 | Z4: Инструмент / устройство
A5: PL-HIST-0004 | B5: 1558 | C5: год | D5: Италия | E5: Неаполь | F5: Джамбаттиста делла Порта | G5: В «Magia Naturalis» описывает камеру-обскуру как зрелищный и практический инструмент наблюдения/рисования. | H5: Оптика / камера-обскура | I5: Камера-обскура как инструмент художника | J5: Камера-обскура входит в европейскую культуру изображения: становится помощником перспективы и точного рисунка. | K5: Кардано и линза | L5: Kepler, портативные камеры-обскуры | M5: Оптическая предпосылка | N5: 4 | O5: PL-001 | P5: SRC-002 | Q5: IMSS / Museo Galileo — Camera Obscura | R5: https://redi.imss.fi.it/inventions/index.php/Camera_Obscura | S5: 4 | T5: Здесь можно показать мост от науки к искусству: камера ещё не фотографирует, но уже помогает изображать реальность. | U5: Иконка художника, который обводит проекцию. | V5: #оптика #искусство #DellaPorta | X5: 40.8518, 14.2681 | Z5: Применение / жанр
A6: PL-HIST-0005 | B6: 1604 | C6: год | D6: Германия | E6: Прага / Линц (контекст Kepler) | F6: Иоганн Кеплер | G6: Использует/закрепляет термин «camera obscura» и анализирует формирование оптического изображения. | H6: Оптика / камера-обскура | I6: Camera obscura | J6: Понятие получает устойчивое научное имя и входит в язык оптики. | K6: Renaissance descriptions of camera obscura | L6: Kepler's Dioptrice and portable camera obscura | M6: Оптическая предпосылка | N6: 3 | O6: PL-001 | P6: SRC-003 | Q6: Max Planck Institute — Camera Obscura PDF | R6: https://www.mpiwg-berlin.mpg.de/sites/default/files/Preprints/P307.pdf | S6: 4 | T6: На карте можно показать, что слова тоже важны: когда явление получает имя, его проще передавать и развивать. | U6: Плашка-термин: CAMERA OBSCURA. | V6: #оптика #Kepler #термин | X6: 50.0755, 14.4378 | Y6: Оптика / терминология | Z6: Терминология / язык
A7: PL-HIST-0006 | B7: 1611 | C7: год | D7: Германия | E7: Линц / Прага | F7: Иоганн Кеплер | G7: В «Dioptrice» развивает понимание линз, проекции и улучшения изображения в оптических системах. | H7: Оптика / камера-обскура | I7: Линзовая камера-обскура | J7: Будущая камера всё больше зависит от оптики: линзы дают контроль над изображением. | K7: Термин camera obscura | L7: Портативные камеры-обскуры и объективы | M7: Оптическая предпосылка | N7: 4 | O7: PL-001 | P7: SRC-003 | Q7: Max Planck Institute — Camera Obscura PDF | R7: https://www.mpiwg-berlin.mpg.de/sites/default/files/Preprints/P307.pdf | S7: 3 | T7: Не перегружать урок формулами; объяснить как «переход от дырочки к оптической системе». | U7: Схема: отверстие → линза → более яркая проекция. | V7: #оптика #линзы #Kepler | W7: Подтвердить конкретные формулировки по первичному тексту Dioptrice. | X7: 48.3069, 14.2858 | Y7: Оптика / камера | Z7: Фундаментальная предпосылка
A8: PL-HIST-0007 | B8: ок. 1620 | C8: примерно | D8: Австрия / Германия | E8: Верхняя Австрия | F8: Иоганн Кеплер | G8: Использует переносную камеру-обскуру в виде палатки для наблюдения и зарисовок ландшафта. | H8: Оптические инструменты | I8: Портативная camera obscura | J8: Камера-обскура становится мобильной: это важный шаг к переносной камере. | K8: Линзовая камера-обскура | L8: Zahn and portable camera designs | M8: Оптическая предпосылка | N8: 3 | O8: PL-001 | P8: SRC-003 | Q8: Max Planck Institute — Camera Obscura PDF | R8: https://www.mpiwg-berlin.mpg.de/sites/default/files/Preprints/P307.pdf | S8: 3 | T8: Хороший визуальный эпизод для рилса: учёный в тёмной палатке ловит изображение мира. | U8: Карта: линия от комнаты к переносной палатке. | V8: #камера-обскура #портативность #Kepler | W8: Проверить год и источники письма Henry Wotton. | X8: 48.3069, 14.2858 | Z8: Инструмент / устройство
A9: PL-HIST-0008 | B9: 1685 | C9: год | D9: Германия | E9: Вюрцбург | F9: Иоганн Цан | G9: Публикует схемы переносных камер-обскур и оптических устройств в «Oculus Artificialis». | H9: Оптические инструменты | I9: Портативная / зеркальная camera obscura | J9: Идея камеры становится почти предметной: устройство уже похоже на будущий фотоаппарат, но без химической фиксации. | K9: Портативные камеры-обскуры XVII века | L9: Фотохимия XVIII века | M9: Оптическая предпосылка | N9: 4 | O9: PL-001 | P9: SRC-004 | Q9: Public Domain Review — Johann Zahn's Oculus Artificialis | R9: https://publicdomainreview.org/collection/images-from-johann-zahn-s-oculus-artificialis-1685 | S9: 4 | T9: Можно показать как «корпус камеры появился раньше фотографии». | U9: Иконка деревянной камеры с зеркалом. | V9: #камера #Zahn #оптика | X9: 49.7913, 9.9534 | Z9: Инструмент / устройство
A10: PL-HIST-0009 | B10: 1727 | C10: год | D10: Германия | E10: Альтдорф / Галле | F10: Иоганн Генрих Шульце | G10: Публикует научное исследование: соли серебра темнеют под действием света, а не тепла. | H10: Фотохимия | I10: Серебряные соли | J10: Появляется химическая половина фотографии: материал может реагировать на свет. | K10: Алхимические наблюдения потемнения серебра | L10: Scheele, Wedgwood, Niépce | M10: Химическая предпосылка | N10: 5 | O10: PL-002 | P10: SRC-005 | Q10: Swiss Camera Museum — Johann Heinrich Schulze | R10: https://www.cameramuseum.ch/en/discover/permanent-exhibition/the-origins-of-photography/the-precursors-johann-heinrich-schulze/ | S10: 5 | T10: Это ключевой мост: камера уже строила изображение, но теперь появился материал, который свет может менять. | U10: Серебряная колба/бутылка, на которой свет оставляет след. | V10: #фотохимия #серебро #Schulze #PL002 | X10: 49.3833, 11.3833 | Z10: Фундаментальная предпосылка
A11: PL-HIST-0010 | B11: 1777 | C11: год | D11: Швеция | E11: Кёпинг / Стокгольм (контекст) | F11: Карл Вильгельм Шееле | G11: Изучает свойства хлорида серебра: потемнение на свету и роль аммиака для растворения/стабилизации соединений серебра. | H11: Фотохимия | I11: Silver chloride / ammonia | J11: Фиксация становится главным нерешённым вопросом: как сделать след света устойчивым. | K11: Schulze and silver salts | L11: Wedgwood and Davy, then Niépce | M11: Химическая предпосылка | N11: 4 | O11: PL-002 | P11: SRC-006 | Q11: Science History Institute — Silver and Sunlight | R11: https://www.sciencehistory.org/stories/magazine/silver-and-sunlight/ | S11: 4 | T11: Новичку объяснить: мало получить изображение — нужно остановить дальнейшее потемнение. | U11: Иконка: след света + знак «зафиксировать». | V11: #фотохимия #фиксаж #серебро | W11: Уточнить связь Scheele с практическим фиксированием: не преувеличивать. | X11: 59.5117, 15.9992 | Y11: Фотохимия / фиксация | Z11: Фундаментальная предпосылка
A12: PL-HIST-0011 | B12: ок. 1800 | C12: примерно | D12: Великобритания | E12: Этрурия / Стаффордшир | F12: Томас Веджвуд | G12: Проводит опыты с бумагой/кожей, обработанными нитратом серебра, пытаясь получать изображения светом. | H12: Фотохимия | I12: Серебряный нитрат на бумаге/коже | J12: Появляется идея фотографического изображения, но проблема сохранения ещё не решена. | K12: Schulze and Scheele | L12: Davy publication, Niépce's experiments | M12: Тупиковая / не получила развития | N12: 4 | O12: PL-002 | P12: SRC-007 | Q12: Swiss Camera Museum — Thomas Wedgwood | R12: https://www.cameramuseum.ch/en/discover/permanent-exhibition/the-origins-of-photography/the-precursors-thomas-wedgwood/ | S12: 4 | T12: Хорошо показать как честную неудачу: попытка почти фотографическая, но изображение исчезает. | U12: Пунктирная линия: «почти получилось, но не закрепилось». | V12: #Wedgwood #фотохимия #неудача | X12: 53.0027, -2.1794 | Y12: Фотохимия / первая фиксация | Z12: Технология / процесс
A13: PL-HIST-0012 | B13: 1802 | C13: год | D13: Великобритания | E13: Лондон / Бристоль | F13: Хамфри Дэви и Томас Веджвуд | G13: Дэви публикует отчёт о методе копирования изображений светом на нитрате серебра. | H13: Фотохимия | I13: Photogenic copying on silver nitrate | J13: Первые эксперименты становятся опубликованным знанием, но без полноценного фиксирования изображения. | K13: Wedgwood experiments | L13: Niépce and Talbot later address permanence | M13: Тупиковая / не получила развития | N13: 4 | O13: PL-002 | P13: SRC-008 | Q13: Bodleian — Talbot Catalogue: Photogenic Drawing | R13: https://talbot.bodleian.ox.ac.uk/2017/02/17/an-account-of-the-processes-employed-in-photogenic-drawing/ | S13: 4 | T13: В лекции: до Ньепса уже были люди, которые понимали направление, но не решили задачу постоянства. | U13: Иконка публикации/лист бумаги, который постепенно темнеет. | V13: #Davy #Wedgwood #публикация | W13: Добавить первичный PDF/текст Journal of the Royal Institution при углублении. | X13: 51.5074, -0.1278 | Y13: Фотохимия / публикация | Z13: Публикация / объявление
A14: PL-HIST-0013 | B14: 1806–1807 | C14: диапазон | D14: Великобритания | E14: Лондон | F14: Уильям Хайд Волластон | G14: Патентует и называет camera lucida — оптический прибор для точного рисования. | H14: Оптические инструменты | I14: Camera lucida | J14: Показывает, что до фотографии общество уже искало способы механизировать точность изображения. | K14: Camera obscura drawing tools | L14: Photography will replace drawing aids for some purposes | M14: Оптическая предпосылка | N14: 3 | O14: межурочный узел | P14: SRC-009 | Q14: Smithsonian NMAH — Camera Lucida | R14: https://americanhistory.si.edu/collections/object/nmah_1184286 | S14: 5 | T14: Это не фотография, но очень полезный узел: люди хотели точного изображения до химической фотографии. | U14: Иконка призмы и руки художника. | V14: #оптика #camera-lucida #рисование | X14: 51.5074, -0.1278 | Z14: Инструмент / устройство
A15: PL-HIST-0014 | B15: 1816 | C15: год | D15: Франция | E15: Сен-Лу-де-Варенн / Ле-Гра | F15: Нисефор Ньепс | G15: Получает исчезающие негативные изображения в камере-обскуре на бумаге с солями серебра. | H15: Гелиография | I15: Silver chloride paper negative | J15: Ньепс впервые подходит к реальной камере-фотографии, но изображение ещё не устойчиво. | K15: Wedgwood/Davy experiments | L15: Niépce switches to bitumen heliography | M15: Переходная технология | N15: 5 | O15: PL-002 | P15: SRC-011 | Q15: Maison Nicéphore Niépce — First experiments | R15: https://bicentennial-of-photography.org/niepce-and-the-invention-of-photography-niepce-s-first-experiments/ | S15: 4 | T15: Важно: это не первый сохранившийся снимок, а первая стадия Ньепса — изображение было, но исчезало. | U15: Светлая линия появляется на бумаге и затем исчезает. | V15: #Niépce #1816 #PL002 #негатив | X15: 46.7828, 4.8892 | Y15: Первая фиксация / проблема постоянства | Z15: Технология / процесс
A16: PL-HIST-0015 | B16: 1822–1825 | C16: диапазон | D16: Франция | E16: Сен-Лу-де-Варенн / Ле-Гра | F16: Нисефор Ньепс | G16: Развивает гелиографию: использует светочувствительный битум для создания устойчивых изображений/копий гравюр. | H16: Гелиография | I16: Bitumen of Judea on metal/stone | J16: Путь меняется: вместо серебряных солей Ньепс ищет материал, который свет делает не темнее, а твёрже/нерастворимее. | K16: 1816 silver-salt negatives | L16: View from the Window at Le Gras | M16: Переходная технология | N16: 4 | O16: PL-002 | P16: SRC-010 | Q16: Harry Ransom Center — The Niépce Heliograph | R16: https://www.hrc.utexas.edu/niepce-heliograph/ | S16: 4 | T16: Для лекции: Ньепс думал не только о камере, но и о механическом копировании изображений. | U16: Узел «гелиография»: солнце превращает покрытие в устойчивый след. | V16: #гелиография #Niépce #битум | W16: Проверить дату 1822 для несохранившейся heliograph copy. | X16: 46.7828, 4.8892 | Z16: Технология / процесс
A17: PL-HIST-0016 | B17: 1826 / 1827 | C17: спорно/уточнить | D17: Франция | E17: Ле-Гра, Сен-Лу-де-Варенн | F17: Нисефор Ньепс | G17: Создаёт «Вид из окна в Ле-Гра» — самое раннее сохранившееся изображение, полученное с помощью камеры-обскуры. | H17: Гелиография | I17: Heliograph on pewter plate | J17: Изображение впервые не просто возникло, а сохранилось до наших дней. | K17: Heliographic experiments | L17: Partnership with Daguerre | M17: Главная линия | N17: 5 | O17: PL-002 | P17: SRC-010 | Q17: Harry Ransom Center — The Niépce Heliograph | R17: https://www.hrc.utexas.edu/niepce-heliograph/ | S17: 5 | T17: Дата встречается как 1826 или 1827; в таблице оставляем спорной/уточняемой. | U17: Главный узел PL-002: окно, свет, металлическая пластина. | V17: #Niépce #перваяфотография #гелиография #PL002 | W17: Уточнить редакционную дату: Harvard даёт 1826, HRC — 1827. | X17: 46.7828, 4.8892 | Y17: Гелиография / первая сохранившаяся фотография | Z17: Ключевой исторический узел | AA17: да
A18: PL-HIST-0017 | B18: 1829 | C18: год | D18: Франция | E18: Париж / Сен-Лу-де-Варенн | F18: Нисефор Ньепс и Луи Дагер | G18: Ньепс и Дагер вступают в формальное партнёрство для развития фотографического процесса. | H18: Дагеротип | I18: Heliography → daguerreotype lineage | J18: Линия Ньепса соединяется с практическими улучшениями Дагера. | K18: Niépce heliography | L18: Daguerreotype announcement | M18: Главная линия | N18: 4 | O18: PL-003 | P18: SRC-010 | Q18: Harry Ransom Center — The Niépce Heliograph | R18: https://www.hrc.utexas.edu/niepce-heliograph/ | S18: 5 | T18: Это не просто смена фамилии: здесь начинается связка Ньепс → Дагер. | U18: Линия на карте: Ле-Гра → Париж. | V18: #Niépce #Daguerre #Франция #PL003 | X18: 48.8566, 2.3522 | Y18: Передача идеи / развитие процесса | Z18: Связь / переход
A19: PL-HIST-0018 | B19: 1833 | C19: год | D19: Франция | E19: Сен-Лу-де-Варенн | F19: Нисефор Ньепс / Луи Дагер | G19: После смерти Ньепса Дагер продолжает работы и в итоге доводит процесс до публичного объявления. | H19: Дагеротип | I19: Daguerreotype lineage | J19: Фотография становится историей не одного человека, а продолжения незавершённой разработки. | K19: Partnership 1829 | L19: 1839 public announcement | M19: Главная линия | N19: 3 | O19: PL-003 | P19: SRC-010 | Q19: Harry Ransom Center — The Niépce Heliograph | R19: https://www.hrc.utexas.edu/niepce-heliograph/ | S19: 4 | T19: Для сериала: Ньепс не увидел публичного триумфа фотографии. | U19: Линия прерывается у Ньепса и продолжается к Дагеру. | V19: #Niépce #Daguerre #история | X19: 46.7828, 4.8892 | Y19: Передача идеи / развитие процесса | Z19: Связь / переход
A20: PL-HIST-0019 | B20: 1834 | C20: год | D20: Великобритания | E20: Лэкок-Эбби | F20: Уильям Генри Фокс Тальбот | G20: Создаёт фотогенные рисунки: предметы кладутся на светочувствительную бумагу и оставляют силуэт. | H20: Фотогенный рисунок / фотограмма | I20: Photogenic drawing | J20: Параллельно французской линии появляется британская ветка: изображение через негативный след на бумаге. | K20: Wedgwood/Davy and silver salts | L20: Calotype and negative-positive process | M20: Главная линия | N20: 5 | O20: PL-004 | P20: SRC-023 | Q20: National Gallery of Canada — The Calotype Process | R20: https://www.gallery.ca/photo-blog/the-calotype-process | S20: 4 | T20: Важно показать как параллельную работу, а не как продолжение Дагера. | U20: Отдельная линия Великобритания: лист растения на бумаге. | V20: #Talbot #photogenic-drawing #PL004 | X20: 51.4136, -2.118 | Z20: Технология / процесс
A21: PL-HIST-0020 | B21: 1835 | C21: год | D21: Великобритания | E21: Лэкок-Эбби | F21: Уильям Генри Фокс Тальбот | G21: Делает ранние маленькие камерные негативы, включая вид окна в Лэкок-Эбби. | H21: Негатив-позитив | I21: Paper negative in camera | J21: Тальбот переносит идею фотогенного рисунка в камеру: бумага становится негативом будущей копии. | K21: Photogenic drawings | L21: 1839 publication and 1841 calotype | M21: Главная линия | N21: 4 | O21: PL-004 | P21: SRC-016 | Q21: The Met — William Henry Fox Talbot | R21: https://www.metmuseum.org/essays/william-henry-fox-talbot-1800-1877-and-the-invention-of-photography | S21: 4 | T21: Можно объяснить: у Тальбота фотография думает не как «одна пластинка», а как система копирования. | U21: Окно Лэкок-Эбби как британская пара к окну Ньепса. | V21: #Talbot #окно #негатив #PL004 | W21: Проверить источник для конкретной даты и объекта Oriel Window. | X21: 51.4136, -2.118 | Z21: Технология / процесс
A22: PL-HIST-0021 | B22: 1837 | C22: год | D22: Франция | E22: Париж | F22: Луи Дагер | G22: Дагер получает более практичный прямой позитив на серебряной пластине и сокращает экспозицию по сравнению с Ньепсом. | H22: Дагеротип | I22: Silver-plated copper plate / direct positive | J22: Фотография становится резче, быстрее и технически убедительнее, но остаётся уникальным изображением. | K22: Niépce-Daguerre partnership | L22: 1839 Académie announcement | M22: Исторически важная ограниченная ветка | N22: 4 | O22: PL-003 | P22: SRC-013 | Q22: The Met — Daguerre and the Invention of Photography | R22: https://www.metmuseum.org/essays/daguerre-1787-1851-and-the-invention-of-photography | S22: 3 | T22: В таблице фиксируем как техническую подготовку к публичному объявлению, но дату/детали уточнить. | U22: Металлическая пластина + резкое изображение. | V22: #Daguerre #дагеротип #PL003 | W22: Уточнить первичный источник и дату 1837. | X22: 48.8566, 2.3522 | Z22: Технология / процесс | AA22: да
A23: PL-HIST-0022 | B23: 7 января 1839 | C23: точная дата | D23: Франция | E23: Париж | F23: Франсуа Араго / Луи Дагер | G23: Французская Академия наук видит результаты процесса Дагера; фотография выходит в публичное научное поле. | H23: Дагеротип | I23: Daguerreotype | J23: Фотография перестаёт быть частной лабораторной тайной и становится событием культуры и науки. | K23: Daguerre's experiments | L23: 19 August 1839 public disclosure | M23: Временная доминирующая линия | N23: 5 | O23: PL-003 | P23: SRC-013 | Q23: The Met — Daguerre and the Invention of Photography | R23: https://www.metmuseum.org/essays/daguerre-1787-1851-and-the-invention-of-photography | S23: 5 | T23: Это сильная сцена: не просто изобретение, а момент публичного признания. | U23: Париж, Академия наук, световая демонстрация. | V23: #Daguerre #Arago #Париж #PL003 | X23: 48.8566, 2.3522 | Y23: Дагеротип / публичное объявление | Z23: Публикация / объявление
A24: PL-HIST-0023 | B24: 19 августа 1839 | C24: точная дата | D24: Франция | E24: Париж | F24: Луи Дагер / французское государство | G24: Процесс дагеротипии официально раскрывается публично; Франция фактически дарит процесс миру. | H24: Дагеротип | I24: Daguerreotype | J24: Дагеротип быстро распространяется по Европе и Америке как первый публично объявленный фотографический процесс. | K24: Academy announcement | L24: Daguerreotypomania and portrait studios | M24: Временная доминирующая линия | N24: 5 | O24: PL-003 | P24: SRC-012 | Q24: Harvard Library — History of Photography Timeline | R24: https://photographpreservationprogram.hsites.harvard.edu/harvards-history-photography-timeline-text-only | S24: 5 | T24: В уроке: 1839 — год, когда фотография стала общественным событием. | U24: Большая точка на Париже и расходящиеся линии по миру. | V24: #1839 #Daguerre #Франция #распространение | X24: 48.8566, 2.3522 | Y24: Дагеротип / распространение | Z24: Публикация / объявление
A25: PL-HIST-0024 | B25: 1839 | C25: год | D25: Великобритания | E25: Лондон | F25: Уильям Генри Фокс Тальбот | G25: Публикует «Some Account of the Art of Photogenic Drawing», представляя свой процесс. | H25: Фотогенный рисунок / фотограмма | I25: Photogenic drawing | J25: Британская линия заявляет о себе почти одновременно с французской, показывая параллельность изобретения фотографии. | K25: 1834–1835 experiments | L25: Calotype patent 1841 | M25: Главная линия | N25: 5 | O25: PL-004 | P25: SRC-012 | Q25: Harvard Library — History of Photography Timeline | R25: https://photographpreservationprogram.hsites.harvard.edu/harvards-history-photography-timeline-text-only | S25: 5 | T25: Идеально для объяснения: Франция дала резкость и публичный эффект, Британия — логику копии. | U25: Две линии на карте: Париж и Лондон одновременно загораются в 1839. | V25: #Talbot #1839 #PL004 | X25: 51.5074, -0.1278 | Y25: Фотогенный рисунок / публикация | Z25: Публикация / объявление
A26: PL-HIST-0025 | B26: 1839 | C26: год | D26: Великобритания | E26: Лондон / Slough | F26: Джон Фредерик Уильям Гершель | G26: Предлагает использовать hyposulphite of soda как фиксирующее средство для серебряных фотографий. | H26: Фиксаж / терминология | I26: Hypo / sodium thiosulfate fixer | J26: Фотография становится практически долговечной: изображение можно остановить от дальнейшего действия света. | K26: Silver-salt image instability | L26: Stable calotypes and later silver processes | M26: Главная линия | N26: 5 | O26: PL-004 | P26: SRC-016 | Q26: The Met — William Henry Fox Talbot | R26: https://www.metmuseum.org/essays/william-henry-fox-talbot-1800-1877-and-the-invention-of-photography | S26: 5 | T26: Сильный смысл: фотография — это не только камера, но и умение остановить свет. | U26: Иконка замка/стоп-символа на изображении. | V26: #Herschel #фиксаж #hypo | X26: 51.5074, -0.1278 | Z26: Технология / процесс
A27: PL-HIST-0026 | B27: 1839 | C27: год | D27: Великобритания | E27: Лондон | F27: Джон Фредерик Уильям Гершель | G27: Вводит/закрепляет термины «photography», «negative» и «positive» в ранней фотографической культуре. | H27: Фиксаж / терминология | I27: Photographic terminology | J27: Язык фотографии формируется: появляются термины, без которых невозможно объяснить негативно-позитивный процесс. | K27: Talbot's paper negatives and photogenic drawings | L27: Calotype and photographic vocabulary | M27: Главная линия | N27: 4 | O27: PL-004 | P27: SRC-017 | Q27: Getty — Sir John F. W. Herschel | R27: https://www.getty.edu/art/collection/person/103KHK | S27: 4 | T27: Можно сделать мини-вставку: терминология — это тоже технология понимания. | U27: Карточка слов: PHOTOGRAPHY / NEGATIVE / POSITIVE. | V27: #Herschel #термины #negative #positive | W27: Уточнить первичные даты употребления терминов в письмах/докладах. | X27: 51.5074, -0.1278 | Z27: Терминология / язык
A28: PL-HIST-0027 | B28: 1839–1840 | C28: диапазон | D28: Франция | E28: Париж | F28: Ипполит Байяр | G28: Разрабатывает прямой позитивный процесс на бумаге, но оказывается в тени Дагера и Тальбота. | H28: Уникальный позитив | I28: Direct positive paper process | J28: Показывает, что история фотографии была многоголосой: не все ветки получили признание и масштаб. | K28: French early photographic experiments | L28: Bayard's staged self-portrait and later history | M28: Исторически важная ограниченная ветка | N28: 3 | O28: межурочный узел | P28: SRC-017 | Q28: Getty — Sir John F. W. Herschel | R28: https://www.getty.edu/art/collection/person/103KHK | S28: 3 | T28: Можно использовать как сюжет о несправедливости истории и «забытых изобретателях». | U28: Пунктирная ветка от Парижа, уходящая в сторону. | V28: #Bayard #direct-positive #забытые | W28: Найти лучший источник именно по процессу Байяра, не только биографию Getty. | X28: 48.8566, 2.3522 | Z28: Технология / процесс
A29: PL-HIST-0028 | B29: 1838 | C29: год | D29: Великобритания | E29: Лондон | F29: Чарльз Уитстон | G29: Представляет стереоскоп и демонстрирует принцип бинокулярного зрения. | H29: Оптические инструменты | I29: Stereoscope | J29: Пока ещё не фотографическая технология, но позже стереофотография станет массовой формой визуального опыта. | K29: Optics of vision | L29: Photographic stereographs in the 1850s | M29: Оптическая предпосылка | N29: 3 | O29: будущие PL | P29: SRC-024 | Q29: Royal Society / Google Arts & Culture — Stereoscopy | R29: https://artsandculture.google.com/story/stereoscopy-the-birth-of-3d-technology-the-royal-society/pwWRTNS-hqDN5g | S29: 4 | T29: Этот узел лучше оставить для будущего раздела о 3D/стереофотографии. | U29: Иконка двух глаз / двух изображений. | V29: #стереоскоп #Wheatstone #3D | X29: 51.5074, -0.1278 | Y29: Оптические инструменты / 3D | Z29: Инструмент / устройство
A30: PL-HIST-0029 | B30: 1840 | C30: год | D30: Великобритания | E30: Лэкок-Эбби | F30: Уильям Генри Фокс Тальбот | G30: Обнаруживает латентное изображение и проявление галловой кислотой: секунды экспозиции дают скрытый след, который можно проявить. | H30: Негатив-позитив | I30: Latent image development | J30: Это резко ускоряет бумажную фотографию: теперь не нужно ждать видимого потемнения во время экспозиции. | K30: Photogenic drawing and camera negatives | L30: Calotype patent 1841 | M30: Главная линия | N30: 5 | O30: PL-004 | P30: SRC-016 | Q30: The Met — William Henry Fox Talbot | R30: https://www.metmuseum.org/essays/william-henry-fox-talbot-1800-1877-and-the-invention-of-photography | S30: 5 | T30: Для новичка: фотография научилась работать со скрытым изображением. | U30: Схема: невидимый след → проявитель → появляется картинка. | V30: #latent-image #Talbot #PL004 | X30: 51.4136, -2.118 | Y30: Негатив-позитив / проявление | Z30: Технология / процесс
A31: PL-HIST-0030 | B31: 1840 | C31: год | D31: США | E31: Нью-Йорк | F31: Джон Уильям Дрейпер | G31: Делает ранние научные дагеротипы, включая одну из первых фотографий Луны. | H31: Дагеротип | I31: Daguerreotype for astronomy | J31: Фотография быстро выходит за пределы портрета и становится научным инструментом. | K31: Daguerreotype public disclosure | L31: Astronomical and scientific photography | M31: Главная линия | N31: 3 | O31: будущие PL | P31: SRC-012 | Q31: Harvard Library — History of Photography Timeline | R31: https://photographpreservationprogram.hsites.harvard.edu/harvards-history-photography-timeline-text-only | S31: 3 | T31: Будущий узел для урока о научной фотографии. | U31: Линия Париж → Нью-Йорк + Луна. | V31: #Draper #астрономия #научнаяфотография | W31: Добавить более авторитетный музейный источник по Draper. | Ветка нормализована к 13 значениям v0.2 — узел межжанровый, решение неоднозначное (см. Подветка). | X31: 40.7128, -74.006 | Y31: Научная фотография | Z31: Научное применение / пример
A32: PL-HIST-0031 | B32: 1841 | C32: год | D32: Великобритания | E32: Лондон / Лэкок-Эбби | F32: Уильям Генри Фокс Тальбот | G32: Патентует калотип: усовершенствованный негативно-позитивный процесс на бумаге. | H32: Негатив-позитив | I32: Calotype / Talbotype | J32: Появляется фундаментальная логика фотографии: один негатив может дать много позитивных отпечатков. | K32: Latent image development 1840 | L32: Salted paper prints and The Pencil of Nature | M32: Главная линия | N32: 5 | O32: PL-004 | P32: SRC-015 | Q32: Library of Congress — Calotype and Daguerreotype | R32: https://blogs.loc.gov/teachers/2018/09/pre-civil-war-photographic-technologies-the-calotype-and-daguerreotype/ | S32: 5 | T32: Ключевой тезис PL-004: калотип менее резкий, чем дагеротип, но его идея победила. | U32: Разветвление: один негатив → несколько отпечатков. | V32: #calotype #Talbot #negative-positive #PL004 | X32: 51.5074, -0.1278 | Z32: Технология / процесс | AA32: да
A33: PL-HIST-0032 | B33: 1841 | C33: год | D33: Великобритания | E33: Лондон / Лэкок-Эбби | F33: Уильям Генри Фокс Тальбот | G33: Солёная бумажная печать становится практическим позитивом с бумажного негатива. | H33: Печать / тиражирование | I33: Salted paper print | J33: Фотография становится печатной системой: негатив и позитив начинают работать вместе. | K33: Calotype negative | L33: Pencil of Nature and albumen print | M33: Главная линия | N33: 4 | O33: PL-004 | P33: SRC-020 | Q33: V&A — Photography Processes and Techniques | R33: https://www.vam.ac.uk/info/collection-selection-boxes-photography-processes-and-techniques | S33: 4 | T33: Для схемы: калотип — это не только негатив, но и контактная печать. | U33: Контактная рамка: негатив лежит на бумаге под стеклом. | V33: #salted-paper #print #Talbot | X33: 51.5074, -0.1278 | Z33: Тиражирование / публикация
A34: PL-HIST-0033 | B34: 1842 | C34: год | D34: Великобритания | E34: Лондон / Slough | F34: Джон Фредерик Уильям Гершель | G34: Изобретает цианотипию — железо-солевой процесс, дающий синий отпечаток. | H34: Печать / тиражирование | I34: Cyanotype | J34: Показывает, что фотография не обязана быть только серебряной; появляется альтернативная печать и будущие blueprint-процессы. | K34: Herschel's photochemistry | L34: Anna Atkins's photographic book | M34: Переходная технология / художественное возрождение | N34: 4 | O34: будущие PL | P34: SRC-018 | Q34: HNOC — Cyanotype Process | R34: https://hnoc.org/virtual-exhibitions/from_daguerreotype_to_digital/cyanotype-process | S34: 5 | T34: Цианотипия идеальна для практического урока: простой, зрелищный процесс. | U34: Синяя ветка на карте. | V34: #cyanotype #Herschel #альтернативныйпроцесс | W34: Ветка нормализована к 13 значениям v0.2 — узел межжанровый, решение неоднозначное (см. Подветка). | X34: 51.5074, -0.1278 | Y34: Цианотипия | Z34: Технология / процесс
A35: PL-HIST-0034 | B35: 1843 | C35: год | D35: Великобритания | E35: Кент | F35: Анна Аткинс | G35: Начинает выпуск «Photographs of British Algae: Cyanotype Impressions» — первой книги, напечатанной и иллюстрированной фотографией. | H35: Печать / тиражирование | I35: Cyanotype photobook | J35: Фотография становится способом научной публикации, а не только экспериментом или портретом. | K35: Cyanotype 1842 | L35: Scientific and documentary photography | M35: Главная линия | N35: 4 | O35: будущие PL | P35: SRC-019 | Q35: Natural History Museum — Anna Atkins's cyanotypes | R35: https://www.nhm.ac.uk/discover/anna-atkins-cyanotypes-the-first-book-of-photographs.html | S35: 5 | T35: Очень важный узел: женщина-фотограф, наука, книга и фотография как документ. | U35: Иконка синей книги с водорослью. | V35: #AnnaAtkins #cyanotype #photobook | X35: 51.2787, 0.5217 | Y35: Фотокнига / научная документация | Z35: Тиражирование / публикация
A36: PL-HIST-0035 | B36: 1844 | C36: год | D36: Великобритания | E36: Лондон | F36: Уильям Генри Фокс Тальбот | G36: Начинает публикацию «The Pencil of Nature» — первой коммерчески изданной книги с фотографическими отпечатками. | H36: Печать / тиражирование | I36: Salted paper prints from calotype negatives | J36: Фотография входит в книгу как новый способ иллюстрации и доказательства. | K36: Calotype and salted paper print | L36: Photographic publishing | M36: Главная линия | N36: 5 | O36: PL-004 | P36: SRC-016 | Q36: The Met — William Henry Fox Talbot | R36: https://www.metmuseum.org/essays/william-henry-fox-talbot-1800-1877-and-the-invention-of-photography | S36: 5 | T36: Сильный мост к бренду PHOTO LAB: фотография становится не только снимком, но и системой распространения знания. | U36: Книга, из которой выходят маленькие отпечатки. | V36: #PencilOfNature #Talbot #книга #PL004 | X36: 51.5074, -0.1278 | Y36: Фотокнига / тиражирование | Z36: Тиражирование / публикация
A37: PL-HIST-0036 | B37: 1847 | C37: год | D37: США | E37: Бостон | F37: Southworth & Hawes | G37: Создают дагеротипы медицинских операций с эфирной анестезией в Massachusetts General Hospital. | H37: Дагеротип | I37: Daguerreotype documentation | J37: Фотография быстро становится инструментом медицинского и научного свидетельства. | K37: Daguerreotype portrait/studio practice | L37: Documentary and medical photography | M37: Главная линия | N37: 3 | O37: будущие PL | P37: SRC-012 | Q37: Harvard Library — History of Photography Timeline | R37: https://photographpreservationprogram.hsites.harvard.edu/harvards-history-photography-timeline-text-only | S37: 4 | T37: Этот узел можно оставить для будущего урока о документальности фотографии. | U37: Иконка больницы/операционной + дагеротип. | V37: #medical-photography #daguerreotype #Boston | W37: Ветка нормализована к 13 значениям v0.2 — узел межжанровый, решение неоднозначное (см. Подветка). | X37: 42.3601, -71.0589 | Y37: Научная / медицинская фотография | Z37: Научное применение / пример
A38: PL-HIST-0037 | B38: 1847 | C38: год | D38: Франция | E38: Лилль / Париж | F38: Луи-Дезире Бланкар-Эврар | G38: Развивает и публикует улучшения бумажных негативно-позитивных процессов во Франции. | H38: Печать / тиражирование | I38: Paper negative-positive process | J38: Французская фотография получает не только дагеротипическую, но и бумажную тиражируемую ветку. | K38: Talbot calotype influence | L38: Albumen paper 1850 | M38: Главная линия | N38: 3 | O38: будущие PL | P38: SRC-017 | Q38: Getty — Sir John F. W. Herschel | R38: https://www.getty.edu/art/collection/person/103KHK | S38: 2 | T38: Пока источник не идеален; оставить как узел на доработку. | U38: Франция получает ответвление бумажной печати. | V38: #BlanquartEvrard #France #paper-process | W38: Найти лучший источник по 1847 публикации Бланкара-Эврара. | X38: 50.6292, 3.0573 | Z38: Распространение / коммерциализация
A39: PL-HIST-0038 | B39: 1848 | C39: год | D39: Франция | E39: Париж | F39: Эдмон Беккерель | G39: Создаёт ранний цветной фотографический процесс на основе серебряно-хлоридного слоя. | H39: Цвет | I39: Early colour photography / photochromatic images | J39: Цвет возникает очень рано, но эта ветка пока не становится практичной массовой фотографией. | K39: Silver-based photochemistry | L39: Autochrome and later colour processes | M39: Исторически важная ограниченная ветка | N39: 3 | O39: будущие PL | P39: SRC-025 | Q39: Getty Conservation Institute — Atlas: Salt Print PDF | R39: https://www.getty.edu/conservation/publications_resources/pdf_publications/pdf/atlas_saltprint.pdf | S39: 3 | T39: На карте: цвет появился рано, но не сразу стал удобным. | U39: Пунктирная цветная ветка от серебряной химии. | V39: #color #Becquerel #раннийцвет | W39: Лучше заменить на специализированный музейный источник по Becquerel. | X39: 48.8566, 2.3522 | Z39: Технология / процесс
A40: PL-HIST-0039 | B40: 1848 | C40: год | D40: США | E40: Филадельфия | F40: Братья Лангенхайм | G40: Вводят первые фотографические фонарные слайды. | H40: Проекция / распространение | I40: Photographic lantern slide | J40: Фотография становится не только отпечатком, но и изображением для публичного показа и обучения. | K40: Daguerreotype and glass support experimentation | L40: Educational projection and slide culture | M40: Переходная технология | N40: 3 | O40: будущие PL | P40: SRC-012 | Q40: Harvard Library — History of Photography Timeline | R40: https://photographpreservationprogram.hsites.harvard.edu/harvards-history-photography-timeline-text-only | S40: 4 | T40: Хороший узел для темы распространения изображений до кино и презентаций. | U40: Фонарный проектор + экран. | V40: #lantern-slide #projection #Langenheim | X40: 39.9526, -75.1652 | Z40: Распространение / коммерциализация
A41: PL-HIST-0040 | B41: 1850 | C41: год | D41: Франция | E41: Лилль | F41: Луи-Дезире Бланкар-Эврар | G41: Изобретает альбуминовую печать, которая станет ведущим типом фотопечати XIX века. | H41: Печать / тиражирование | I41: Albumen print | J41: Печать становится более детальной, тональной и удобной для массовой фотографии XIX века. | K41: Salted paper print | L41: Wet collodion negative + albumen print dominance | M41: Главная линия | N41: 5 | O41: будущие PL | P41: SRC-020 | Q41: V&A — Photography Processes and Techniques | R41: https://www.vam.ac.uk/info/collection-selection-boxes-photography-processes-and-techniques | S41: 5 | T41: Важный мост к мокрому коллодию: резкий стеклянный негатив + альбуминовая бумага = визуальный язык XIX века. | U41: Яичный белок/лист бумаги + стеклянный негатив. | V41: #albumen #print #BlanquartEvrard | X41: 50.6292, 3.0573 | Z41: Тиражирование / публикация
A42: PL-HIST-0041 | B42: 1851 | C42: год | D42: Великобритания | E42: Лондон | F42: Фредерик Скотт Арчер | G42: Публикует мокрый коллодионный процесс: стеклянная пластина покрывается коллодием, сенсибилизируется, экспонируется и проявляется влажной. | H42: Мокрый коллодий | I42: Wet collodion glass negative | J42: Соединяет резкость стеклянного носителя и тиражируемость негативно-позитивной системы. | K42: Daguerreotype sharpness + calotype reproducibility problem | L42: Albumen prints, ambrotypes, tintypes, documentary photography | M42: Главная линия / временная доминирующая линия | N42: 5 | O42: PL-005 | P42: SRC-021 | Q42: National Science and Media Museum — Frederick Scott Archer | R42: https://blog.scienceandmediamuseum.org.uk/photography-a-z-frederick-scott-archer-wet-collodion-process/ | S42: 5 | T42: Ключ PL-005: резкость дагеротипа и тираж калотипа наконец встретились. | U42: Главный узел: стеклянная влажная пластина + таймер 15 минут. | V42: #wet-collodion #Archer #PL005 | X42: 51.5074, -0.1278 | Z42: Технология / процесс | AA42: да
A43: PL-HIST-0042 | B43: 1851–1880-е | C43: диапазон | D43: Великобритания / глобально | E43: Лондон → Европа / Америка | F43: Фотографы мокрого коллодия | G43: Мокрый коллодий становится доминирующим процессом на несколько десятилетий. | H43: Мокрый коллодий | I43: Wet collodion negative | J43: Фотография становится более резкой, воспроизводимой и пригодной для документальных задач, но требует мобильной лаборатории. | K43: Archer's publication | L43: Dry plates replace wet collodion later | M43: Временная доминирующая линия | N43: 5 | O43: PL-005 | P43: SRC-021 | Q43: National Science and Media Museum — Frederick Scott Archer | R43: https://blog.scienceandmediamuseum.org.uk/photography-a-z-frederick-scott-archer-wet-collodion-process/ | S43: 5 | T43: Важно: это не тупик сразу; это главный мост середины XIX века. | U43: Широкие линии от Лондона по Европе и Америке. | V43: #wet-collodion #dominant-process #PL005 | X43: 51.5074, -0.1278 | Y43: Мокрый коллодий / распространение | Z43: Распространение / коммерциализация
A44: PL-HIST-0043 | B44: 1851 | C44: год | D44: Великобритания | E44: Лондон | F44: Фредерик Скотт Арчер | G44: Показывает практическую формулу мокрого коллодия: коллодий + йодид калия + нитрат серебра + немедленное проявление/фиксаж. | H44: Мокрый коллодий | I44: Collodion + silver nitrate | J44: Процесс требует скорости и дисциплины: пластину надо подготовить, снять и проявить пока она влажная. | K44: Photographic chemistry and glass supports | L44: Portable darkrooms and field photography | M44: Главная линия / временная доминирующая линия | N44: 5 | O44: PL-005 | P44: SRC-021 | Q44: National Science and Media Museum — Frederick Scott Archer | R44: https://blog.scienceandmediamuseum.org.uk/photography-a-z-frederick-scott-archer-wet-collodion-process/ | S44: 5 | T44: Для урока: здесь появляется драматургия «15 минут, пока пластина влажная». | U44: Схема-алгоритм из 5 шагов вокруг стеклянной пластины. | V44: #химия #коллодий #стекло #PL005 | X44: 51.5074, -0.1278 | Y44: Мокрый коллодий / химия | Z44: Технология / процесс
A45: PL-HIST-0044 | B45: 1853 | C45: год | D45: Великобритания | E45: Лондон | F45: Фредерик Скотт Арчер | G45: Демонстрирует складную коллодионную камеру, совмещённую с мини-тёмной комнатой. | H45: Мокрый коллодий | I45: Folding collodion camera / portable darkroom | J45: Техническая проблема процесса решается конструкцией: фотографу нужно работать с пластиной на месте. | K45: Wet collodion process 1851 | L45: Field photography and mobile darkrooms | M45: Переходная технология | N45: 4 | O45: PL-005 | P45: SRC-021 | Q45: National Science and Media Museum — Frederick Scott Archer | R45: https://blog.scienceandmediamuseum.org.uk/photography-a-z-frederick-scott-archer-wet-collodion-process/ | S45: 5 | T45: Хороший визуальный сюжет: камера как чемодан-лаборатория. | U45: Иконка камеры с рукавами и стеклянной пластиной внутри. | V45: #Archer #collodion-camera #PL005 | X45: 51.5074, -0.1278 | Y45: Мокрый коллодий / камера | Z45: Инструмент / устройство
A46: PL-HIST-0045 | B46: ок. 1853 | C46: примерно | D46: Великобритания / США | E46: Лондон / Бостон | F46: Фотографы коллодионного процесса | G46: Появляется коллодионный позитив на стекле, позже известный как амбротип. | H46: Уникальный позитив | I46: Ambrotype / collodion positive | J46: Мокрый коллодий даёт не только негативы для печати, но и дешёвые уникальные портреты. | K46: Wet collodion process | L46: Cutting patent 1854 and tintype | M46: Исторически важная ограниченная ветка | N46: 4 | O46: PL-005 | P46: SRC-022 | Q46: Library of Congress — Ambrotypes and Tintypes | R46: https://www.loc.gov/collections/liljenquist-civil-war-photographs/articles-and-essays/ambrotypes-and-tintypes/ | S46: 4 | T46: В PL-005 можно сказать: один процесс породил сразу несколько форм — негатив, амбротип, тинтайп. | U46: От основной коллодионной ветки отходит стеклянный позитив. | V46: #ambrotype #collodion-positive #PL005 | X46: 51.5074, -0.1278 | Y46: Уникальный позитив / мокрый коллодий | Z46: Технология / процесс
A47: PL-HIST-0046 | B47: 1854 | C47: год | D47: США | E47: Бостон | F47: Джеймс Амброуз Каттинг | G47: Патентует улучшения амбротипного процесса. | H47: Уникальный позитив | I47: Ambrotype | J47: Коллодионный позитив становится коммерческой портретной практикой, особенно в 1850–1860-х. | K47: Collodion positive around 1853 | L47: Tintype and paper print competition | M47: Исторически важная ограниченная ветка | N47: 3 | O47: PL-005 | P47: SRC-022 | Q47: Library of Congress — Ambrotypes and Tintypes | R47: https://www.loc.gov/collections/liljenquist-civil-war-photographs/articles-and-essays/ambrotypes-and-tintypes/ | S47: 5 | T47: Для карты: ветка не главная, но культурно важная — доступные портреты. | U47: Портрет на стекле с тёмной подложкой. | V47: #ambrotype #Cutting #portrait | X47: 42.3601, -71.0589 | Y47: Уникальный позитив / мокрый коллодий | Z47: Технология / процесс
A48: PL-HIST-0047 | B48: 1855–1881 | C48: диапазон | D48: Европа / США | E48: Студии и полевые лаборатории | F48: Фотографы мокрого коллодия | G48: Мокрый коллодионный негатив + альбуминовая печать формируют классический визуальный язык середины XIX века. | H48: Мокрый коллодий | I48: Wet collodion negative + albumen print | J48: Появляется связка: резкий стеклянный негатив даёт детальные бумажные отпечатки. | K48: Albumen print 1850 + wet collodion 1851 | L48: Dry plate and gelatin processes later | M48: Главная линия / временная доминирующая линия | N48: 5 | O48: PL-005 | P48: SRC-020 | Q48: V&A — Photography Processes and Techniques | R48: https://www.vam.ac.uk/info/collection-selection-boxes-photography-processes-and-techniques | S48: 5 | T48: Это финальная формула PL-005: не один процесс, а связка негатив + печать. | U48: Двойной узел: стеклянная пластина → альбуминовый отпечаток. | V48: #wet-collodion #albumen #print #PL005 | Y48: Мокрый коллодий + печать | Z48: Тиражирование / публикация
A49: PL-HIST-0048 | B49: 1856 | C49: год | D49: США / Великобритания | E49: США / Великобритания | F49: Hamilton Smith / William Kloen / другие | G49: Тинтайп/ферротип закрепляется как дешёвый прямой позитив на лакированном металле, связанный с мокрым коллодием. | H49: Уникальный позитив | I49: Tintype / ferrotype | J49: Фотография становится более дешёвой, прочной и мобильной для массового портрета. | K49: Ambrotype and wet collodion | L49: Civil War era portraiture and itinerant photography | M49: Исторически важная ограниченная ветка / художественное возрождение | N49: 3 | O49: PL-005 | P49: SRC-022 | Q49: Library of Congress — Ambrotypes and Tintypes | R49: https://www.loc.gov/collections/liljenquist-civil-war-photographs/articles-and-essays/ambrotypes-and-tintypes/ | S49: 4 | T49: Это ветка массового портрета: не главная линия к плёнке, но важная социально. | U49: Металлическая пластинка-портрет, ярмарка/палатка. | V49: #tintype #ferrotype #collodion #portrait | W49: Уточнить авторство/патенты 1856 по отдельным источникам. | Y49: Уникальный позитив / массовый портрет | Z49: Технология / процесс
A50: PL-HIST-0049 | B50: 1871 | C50: год | D50: Великобритания | E50: Лондон (публикация) | F50: Ричард Лич Мэддокс | G50: Публикует рабочий метод желатино-бромидной сухой пластины: светочувствительная эмульсия на стекле может высохнуть и всё равно сохранять способность к экспонированию. | H50: Негатив-позитив | I50: Gelatino-bromide dry plate | J50: Пластина больше не обязана быть влажной в момент съёмки: фотография делает первый серьёзный шаг от полевой лаборатории к заранее подготовленному материалу. | K50: Мокрый коллодий требовал немедленно готовить, снимать и проявлять пластину | L50: Эксперименты Бёрджесса, Кеннетта и Беннетта; коммерческие сухие пластины | M50: Главная линия | N50: 5 | O50: PL-006 | P50: SRC-027 | Q50: National Science and Media Museum — Kodak and Ilford camera factories | R50: https://www.scienceandmediamuseum.org.uk/objects-and-stories/kodak-ilford-camera-factories-1930s | S50: 5 | T50: В уроке важно объяснить: Мэддокс не сделал фотографию моментально массовой, но открыл принцип — стеклянную пластину можно готовить заранее. | U50: На карте: влажная красная линия коллодия переходит в сухую стеклянную пластину с желатиновой эмульсией. | V50: #PL006 #dry-plate #Maddox #gelatin #negative-positive | W50: Уточнить, стоит ли привязывать город к Лондону как месту публикации, а не к месту экспериментов. | X50: 51.5074, -0.1278 | Y50: Сухие желатиновые пластины / химия | Z50: Технология / процесс | AA50: да
A51: PL-HIST-0050 | B51: 1874 | C51: год | D51: Великобритания | E51: Ливерпуль | F51: Liverpool Dry Plate Company / ранние производители | G51: Начинаются коммерческие продажи желатиновых сухих пластин; одним из первых производителей называется Liverpool Dry Plate Company. | H51: Негатив-позитив | I51: Commercial gelatin dry plates | J51: Фотограф впервые может не готовить пластину сам перед съёмкой, а купить готовый чувствительный материал. | K51: Публикация Мэддокса 1871 и последующие улучшения | L51: Беннетт повышает чувствительность эмульсии; производство становится практичнее | M51: Распространение / коммерциализация | N51: 4 | O51: PL-006 | P51: SRC-027 | Q51: National Science and Media Museum — Kodak and Ilford camera factories | R51: https://www.scienceandmediamuseum.org.uk/objects-and-stories/kodak-ilford-camera-factories-1930s | S51: 4 | T51: Для новичка: это переход от «сам себе химик» к покупке готового фотоматериала. | U51: Иконка фабричной коробки сухих пластин рядом со стеклянной пластиной. | V51: #PL006 #LiverpoolDryPlate #commercial #dry-plate | W51: Проверить по отдельному источнику точное название компании и формат первых продаж. | X51: 53.4084, -2.9916 | Y51: Сухие желатиновые пластины / коммерциализация | Z51: Распространение / коммерциализация
A52: PL-HIST-0051 | B52: 1878 | C52: год | D52: Великобритания | E52: Лондон | F52: Чарльз Харпер Беннетт | G52: Предлагает нагревать/«созревать» желатиновую эмульсию перед нанесением на стекло, резко повышая её светочувствительность. | H52: Негатив-позитив | I52: Ripened gelatin-bromide emulsion | J52: Сухая пластина становится достаточно быстрой для коротких выдержек и съёмки более живого движения. | K52: Желатино-бромидная сухая пластина Мэддокса | L52: Сухие пластины входят в широкое производство и начинают вытеснять мокрый коллодий | M52: Главная линия | N52: 5 | O52: PL-006 | P52: SRC-029 | Q52: Swiss Camera Museum — Gelatine bromide plates | R52: https://www.cameramuseum.ch/en/discover/permanent-exhibition/the-plate-era/gelatine-bromide-plates/ | S52: 5 | T52: Драматургия урока: сухая пластина была удобной, но сначала слабой; Беннетт сделал её действительно быстрой. | U52: Иконка нагрева эмульсии + секундомер/короткая выдержка. | V52: #PL006 #Bennett #gelatin-bromide #instantaneous | X52: 51.5074, -0.1278 | Y52: Сухие желатиновые пластины / повышение чувствительности | Z52: Технология / процесс
A53: PL-HIST-0052 | B53: 1878 | C53: год | D53: Великобритания / Европа | E53: Лондон / промышленные центры | F53: Производители фотоматериалов | G53: После улучшений сухие желатиновые пластины переходят к общему производству и начинают быстро заменять мокрый коллодионный процесс. | H53: Негатив-позитив | I53: Manufactured gelatin dry plates | J53: Фотографу больше не нужна переносная тёмная комната на каждую съёмку; процесс становится удобнее, чище и предсказуемее. | K53: Улучшение чувствительности эмульсии Беннеттом | L53: Фабричное производство пластин и рост любительской фотографии | M53: Главная линия / временная доминирующая линия | N53: 5 | O53: PL-006 | P53: SRC-028 | Q53: National Science and Media Museum — A brief guide to photographs on glass | R53: https://blog.scienceandmediamuseum.org.uk/a-brief-guide-to-photographs-on-glass/ | S53: 5 | T53: Это ключевой смысл PL-006: фотография освобождается от немедленной химической гонки мокрого коллодия. | U53: Линия: палатка-лаборатория исчезает, остаётся камера + коробка готовых пластин. | V53: #PL006 #manufacture #dry-plate #wet-collodion | X53: 51.5074, -0.1278 | Y53: Сухие желатиновые пластины / переход от мокрого коллодия | Z53: Связь / переход
A54: PL-HIST-0053 | B54: конец 1870-х – 1880-е | C54: диапазон | D54: Европа / США | E54: распределённый процесс | F54: Фотографы и производители сухих пластин | G54: Более быстрые сухие пластины позволяют увереннее снимать события, повседневную жизнь и движение, а не только тщательно поставленные сцены. | H54: Негатив-позитив | I54: Fast dry plate / instantaneous photography | J54: Сокращение выдержки меняет не только технику, но и визуальный язык: фотография становится ближе к «моменту». | K54: Беннетт повышает чувствительность эмульсии | L54: Распространение портативных камер, любительской съёмки и последующий переход к плёнке | M54: Главная линия | N54: 4 | O54: PL-006 | P54: SRC-030 | Q54: Cornell Library — Dawn's Early Light: Towards Modern Photography | R54: https://rmc.library.cornell.edu/DawnsEarlyLight/exhibition/modernphotography/index.html | S54: 4 | T54: Для лекции: сухая пластина — это не просто удобство хранения, а новая скорость взгляда. | U54: На карте: рядом с пластиной появляется значок бегущего человека/движения. | V54: #PL006 #instantaneous #motion #dry-plate | Y54: Сухие желатиновые пластины / скорость и движение | Z54: Применение / жанр
A55: PL-HIST-0054 | B55: 1880 | C55: год | D55: США | E55: Рочестер, Нью-Йорк | F55: Джордж Истмен | G55: Начинает коммерчески производить сухие пластины в США и масштабировать их изготовление. | H55: Негатив-позитив | I55: Eastman dry plates | J55: Сухая пластина становится не только европейским техническим процессом, но и основой американской фотоиндустрии. | K55: Коммерческие сухие пластины в Великобритании и улучшения Беннетта | L55: Eastman Dry Plate Company; дальнейший поиск замены стекла гибким носителем | M55: Распространение / коммерциализация | N55: 4 | O55: PL-006 | P55: SRC-031 | Q55: Kodak — History | R55: https://www.kodak.com/en/company/page/history/ | S55: 5 | T55: Здесь появляется мост к Kodak: сначала Истмен работает не с плёнкой, а именно с сухими пластинами. | U55: Иконка Рочестера/фабрики + коробка Eastman dry plates. | V55: #PL006 #Eastman #Rochester #dry-plate #Kodak | X55: 43.1566, -77.6088 | Y55: Сухие желатиновые пластины / американская индустрия | Z55: Распространение / коммерциализация
A56: PL-HIST-0055 | B56: 1881 | C56: точная дата | D56: США | E56: Рочестер, Нью-Йорк | F56: Джордж Истмен / Генри Стронг | G56: 1 января 1881 года создаётся Eastman Dry Plate Company. | H56: Негатив-позитив | I56: Eastman Dry Plate Company | J56: Промышленная логика фотографии усиливается: производство чувствительного материала становится самостоятельным бизнесом. | K56: Истмен начинает коммерческое производство сухих пластин в 1880 | L56: Eastman Dry Plate and Film Company; рулонные носители и Kodak | M56: Распространение / коммерциализация | N56: 4 | O56: PL-006 | P56: SRC-032 | Q56: Kodak — George Eastman History | R56: https://www.kodak.com/en/company/page/george-eastman-history/ | S56: 5 | T56: Это важный узел для перехода: Kodak родился не сразу как камера для всех, а из бизнеса сухих пластин. | U56: На карте: фабрика/брендовый узел между сухими пластинами и будущей плёнкой. | V56: #PL006 #EastmanDryPlateCompany #Rochester #Kodak | X56: 43.1566, -77.6088 | Y56: Сухие желатиновые пластины / бизнес и масштабирование | Z56: Распространение / коммерциализация
A57: PL-HIST-0056 | B57: 1880–1900 | C57: диапазон | D57: Европа / США | E57: распределённый процесс | F57: Фотографы конца XIX века | G57: Желатиновые сухие пластинные негативы становятся наиболее распространённой формой негативов примерно с 1880 по 1900 год. | H57: Негатив-позитив | I57: Gelatin dry plate negative | J57: На два десятилетия сухая пластина становится нормой профессиональной и серьёзной любительской фотографии. | K57: Производство сухих пластин и рост чувствительности эмульсий | L57: Гибкая плёнка постепенно заменяет стеклянную пластину в массовой фотографии | M57: Главная линия / временная доминирующая линия | N57: 4 | O57: PL-006 | P57: SRC-033 | Q57: Smithsonian Institution Archives — Gelatin Dry Plate Negatives | R57: https://siarchives.si.edu/blog/highlight-photo-cold-vault-gelatin-dry-plate-negatives | S57: 5 | T57: Формула для урока: мокрый коллодий был революцией середины века, сухая пластина — нормой конца века. | U57: Широкая полоса на таймлайне 1880–1900: «эпоха сухих пластин». | V57: #PL006 #1880s #dry-plate-negative #glass-negative | Y57: Сухие желатиновые пластины / доминирующая практика | Z57: Ключевой исторический узел
A58: PL-HIST-0057 | B58: 1880-е | C58: диапазон | D58: Европа / США | E58: распределённый процесс | F58: Профессиональные и любительские фотографы | G58: Сухие пластины можно было экспонировать в одном месте, а проявлять позже в тёмной комнате; это убирало зависимость от немедленной полевой химии. | H58: Негатив-позитив | I58: Prepared dry plates / delayed development | J58: Фотограф получает свободу маршрута: съёмка и проявка впервые заметно расходятся во времени и пространстве. | K58: Wet collodion field darkroom | L58: Portable cameras, amateur photography and roll film systems | M58: Главная линия | N58: 5 | O58: PL-006 | P58: SRC-034 | Q58: George Eastman Museum — Dry Plates in the Woods | R58: https://www.eastman.org/blog/dry-plates-woods-using-19th-century-photographic-processes-capture-letchworth-state-park | S58: 5 | T58: Очень понятная фраза для новичка: теперь не нужно тащить лабораторию за каждым кадром. | U58: Маршрутная линия: фотограф уходит из лаборатории на улицу/в лес, а проявляет позже. | V58: #PL006 #mobility #delayed-development #dry-plate | Y58: Сухие желатиновые пластины / мобильность | Z58: Связь / переход
A59: PL-HIST-0058 | B59: 1880-е | C59: диапазон | D59: США / Великобритания | E59: Рочестер / промышленные центры | F59: Джордж Истмен и производители фотоматериалов | G59: Опыт с желатиновыми сухими пластинами подталкивает производителей к следующей проблеме: заменить тяжёлое и хрупкое стекло более лёгким гибким носителем. | H59: Негатив-позитив | I59: Bridge from glass plates to roll film | J59: PL-006 логически открывает PL-007: после свободы от мокрой химии фотография начинает освобождаться от стеклянной пластины. | K59: Сухие желатиновые пластины как удобный готовый негативный материал | L59: Рулонная плёнка, Kodak camera 1888, массовая любительская фотография | M59: Связь / переход | N59: 5 | O59: PL-006 | P59: SRC-031 | Q59: Kodak — History | R59: https://www.kodak.com/en/company/page/history/ | S59: 4 | T59: Это интрига на следующий урок: фотография стала сухой, но пока ещё стеклянной. | U59: Стеклянная пластина превращается в гибкую ленту/рулон — стрелка к будущему PL-007. | V59: #PL006 #bridge #roll-film #Kodak #future-PL | W59: При планировании PL-007 уточнить отдельными источниками Eastman-Walker roll holder и даты ранней рулонной плёнки. | X59: 43.1566, -77.6088 | Y59: Сухие желатиновые пластины / мост к плёнке | Z59: Связь / переход
A60: PL-HIST-0059 | B60: 1884 | C60: год | D60: США | E60: Рочестер, Нью-Йорк | F60: Джордж Истмен / Eastman Dry Plate and Film Company | G60: Компания Истмена меняет акцент с одних сухих пластин на поиск более удобного рулонного носителя для фотографии. | H60: Негатив-позитив | I60: Eastman Dry Plate and Film Company / roll-film direction | J60: После сухих пластин следующей проблемой становится не химия, а носитель: стекло нужно заменить чем-то гибким и лёгким. | K60: Сухие желатиновые пластины освободили фотографа от мокрой лаборатории, но не от тяжёлого стекла. | L60: Eastman-Walker roll holder и бумажная рулонная плёнка | M60: Связь / переход | N60: 4 | O60: PL-007 | P60: SRC-031 | Q60: Kodak — History | R60: https://www.kodak.com/en/company/page/history/ | S60: 4 | T60: В уроке это мост: фотография уже стала сухой, но ещё остаётся стеклянной. Истмен ищет следующий уровень удобства. | U60: Стеклянная пластина на карте превращается в намотанную ленту. | V60: #PL007 #Eastman #roll-film #Rochester #bridge | W60: Уточнить, нужна ли отдельная строка по юридическому переименованию компании 1884 или достаточно оставить как контекст. | X60: 43.1566, -77.6088 | Y60: Рулонная плёнка / бизнес-переход | Z60: Связь / переход
A61: PL-HIST-0060 | B61: 1885 | C61: год | D61: США | E61: Рочестер, Нью-Йорк | F61: Джордж Истмен / Уильям Холл Уокер | G61: Появляется Eastman-Walker roll holder — держатель, позволявший использовать рулонный носитель в камерах, рассчитанных на пластины. | H61: Негатив-позитив | I61: Eastman-Walker roll holder | J61: Камера начинает работать не с одиночными стеклянными пластинами, а с последовательностью кадров на рулоне. | K61: Сухая пластина как готовый негативный материал | L61: American Film и первые попытки коммерческого рулонного процесса | M61: Главная линия | N61: 5 | O61: PL-007 | P61: SRC-035 | Q61: Science Museum Group — Eastman-Walker roll holder | R61: https://collection.sciencemuseumgroup.org.uk/objects/co15879/eastman-walker-roll-holder | S61: 5 | T61: Для новичка: рулонная плёнка сначала вошла не как маленькая камера Kodak, а как приставка/держатель для уже существующих камер. | U61: На карте: рядом с камерой появляется рулонный модуль вместо стопки стеклянных пластин. | V61: #PL007 #EastmanWalker #roll-holder #Rochester | X61: 43.1566, -77.6088 | Y61: Рулонная плёнка / держатель | Z61: Инструмент / устройство
A62: PL-HIST-0061 | B62: 1885 | C62: год | D62: США | E62: Рочестер, Нью-Йорк | F62: Джордж Истмен / Eastman Dry Plate and Film Company | G62: Eastman American Film с бумажной основой вводится вместе с Eastman-Walker roll holder и предлагается профессиональным фотографам. | H62: Негатив-позитив | I62: American Film / paper-based roll film | J62: Рулонный носитель становится реальным коммерческим продуктом, но бумажная основа ещё даёт ограничения по качеству. | K62: Eastman-Walker roll holder | L62: Kodak camera 1888 и прозрачная рулонная плёнка 1889 | M62: Переходная технология | N62: 4 | O62: PL-007 | P62: SRC-036 | Q62: George Eastman Museum — Two rare rolls of early Kodak film | R62: https://www.eastman.org/two-rare-rolls-early-kodak-film-acquired-george-eastman-museum | S62: 5 | T62: Важно показать честно: первая рулонная плёнка была удобнее стекла, но ещё не идеальна по изображению. | U62: Пунктирная лента: рулон уже появился, но ещё требует улучшения. | V62: #PL007 #AmericanFilm #paper-roll-film #Eastman | X62: 43.1566, -77.6088 | Y62: Рулонная плёнка / бумажная основа | Z62: Технология / процесс
A63: PL-HIST-0062 | B63: 1887 | C63: год | D63: США | E63: Ньюарк, Нью-Джерси | F63: Ганнибал Гудвин | G63: Гудвин подаёт патентную заявку на прозрачную гибкую фотографическую плёнку на нитроцеллюлозной основе. | H63: Негатив-позитив | I63: Flexible transparent nitrocellulose film | J63: Рулонная фотография получает направление к прозрачной гибкой основе, которая лучше подходит для качественного негатива и будущего кино. | K63: Ограничения бумажной рулонной плёнки | L63: Прозрачная плёнка Eastman/Reichenbach и патентные споры вокруг целлулоидной основы | M63: Исторически важная ограниченная ветка | N63: 4 | O63: PL-007 | P63: SRC-037 | Q63: National Inventors Hall of Fame — Hannibal Goodwin | R63: https://www.invent.org/inductees/hannibal-goodwin | S63: 4 | T63: Этот узел нужен как параллельная ветка: история плёнки — не только Истмен, но и спорная линия Гудвина. | U63: От основной линии Kodak отходит пунктирная ветка к Ньюарку: изобретатель вне большой фабрики. | V63: #PL007 #Goodwin #celluloid #transparent-film #patent | W63: Проверить формулировку: заявка 1887, патент выдан позже; не писать как мгновенно утверждённый патент. | X63: 40.7357, -74.1724 | Y63: Рулонная плёнка / целлулоидная основа | Z63: Технология / процесс
A64: PL-HIST-0063 | B64: 1888 | C64: год | D64: США | E64: Рочестер, Нью-Йорк | F64: Джордж Истмен / Kodak | G64: Появляется первая камера Kodak: простая box-camera, заранее заряженная рулоном на 100 снимков. | H64: Негатив-позитив | I64: Original Kodak camera / roll-film camera | J64: Фотография становится не только технологией профессионалов: пользователь нажимает кнопку, а сложную обработку берёт на себя компания. | K64: American Film и попытки заменить стеклянную пластину рулонным носителем | L64: Сервисная модель Kodak и массовая любительская фотография | M64: Главная линия | N64: 5 | O64: PL-007 | P64: SRC-038 | Q64: Smithsonian NMAH — Original Kodak Camera, Serial No. 540 | R64: https://americanhistory.si.edu/collections/object/nmah_760118 | S64: 5 | T64: Это флагман PL-007: камера Kodak изменила не только материал, но и саму роль фотографа. | U64: Главный узел: маленькая box-camera с рулоном внутри, от неё расходится линия к массовой фотографии. | V64: #PL007 #Kodak #roll-film-camera #Eastman #Rochester | X64: 43.1566, -77.6088 | Y64: Рулонная плёнка / Kodak camera | Z64: Ключевой исторический узел | AA64: да
A65: PL-HIST-0064 | B65: 1888 | C65: год | D65: США | E65: Рочестер, Нью-Йорк | F65: Джордж Истмен / Kodak | G65: Kodak продаёт камеру уже заряженной плёнкой; после съёмки всю камеру отправляют в Рочестер для проявки, печати и перезарядки. | H65: Негатив-позитив | I65: Kodak processing service model | J65: Фотограф больше не обязан быть химиком и печатником: процесс съёмки отделяется от лабораторной обработки. | K65: Original Kodak camera 1888 | L65: Слоган «You press the button, we do the rest» и рост любительской фотографии | M65: Распространение / коммерциализация | N65: 5 | O65: PL-007 | P65: SRC-039 | Q65: The Met — Kodak and the Rise of Amateur Photography | R65: https://www.metmuseum.org/essays/kodak-and-the-rise-of-amateur-photography | S65: 5 | T65: Главная мысль для лекции: Kodak продавал не просто камеру, а целую систему — камера + плёнка + обработка. | U65: Маршрут: камера у пользователя → фабрика в Рочестере → готовые отпечатки возвращаются обратно. | V65: #PL007 #Kodak #service-model #amateur-photography | X65: 43.1566, -77.6088 | Y65: Рулонная плёнка / сервисная модель | Z65: Распространение / коммерциализация
A66: PL-HIST-0065 | B66: 4 сентября 1888 | C66: точная дата | D66: США | E66: Рочестер, Нью-Йорк | F66: Джордж Истмен / Kodak | G66: Истмен получает патент на камеру Kodak и регистрирует товарный знак Kodak. | H66: Негатив-позитив | I66: Kodak patent and trademark | J66: Рулонная камера становится не только техническим устройством, но и брендом, который легко запомнить и продвигать. | K66: Original Kodak camera 1888 | L66: Переименование компании и формирование Kodak как массового фотобренда | M66: Распространение / коммерциализация | N66: 4 | O66: PL-007 | P66: SRC-040 | Q66: George Eastman Museum — From the Camera Obscura to the Revolutionary Kodak | R66: https://www.eastman.org/camera-obscura-revolutionary-kodak | S66: 5 | T66: Этот узел можно использовать коротко: фотография входит в эпоху бренда, рекламы и простого обещания пользователю. | U66: На карте: рядом с Рочестером появляется знак KODAK как брендовый маяк. | V66: #PL007 #Kodak #patent #trademark #brand | X66: 43.1566, -77.6088 | Y66: Рулонная плёнка / патент и бренд | Z66: Публикация / объявление
A67: PL-HIST-0066 | B67: 1889 | C67: год | D67: США | E67: Рочестер, Нью-Йорк | F67: Джордж Истмен / Генри Райхенбах | G67: На рынок выходит первая коммерческая прозрачная рулонная плёнка, усовершенствованная Истменом и его химиком. | H67: Негатив-позитив | I67: Commercial transparent roll film | J67: Плёнка становится более удобной для качественного негатива и открывает путь не только фотографии, но и движущемуся изображению. | K67: Бумажная American Film и поиски прозрачной гибкой основы | L67: Развитие кинематографа и дальнейшая массовая плёночная фотография | M67: Главная линия | N67: 5 | O67: PL-007 | P67: SRC-041 | Q67: Kodak — Chronology of Film | R67: https://www.kodak.com/en/motion/page/chronology-of-film/ | S67: 5 | T67: В уроке важно отличить: Kodak 1888 уже был рулонной камерой, но прозрачная рулонная плёнка как коммерческий материал — отдельный шаг 1889 года. | U67: Рулон из полупрозрачной ленты, уходящий от фотографии к кино. | V67: #PL007 #transparent-roll-film #Reichenbach #Eastman #motion-picture | X67: 43.1566, -77.6088 | Y67: Рулонная плёнка / прозрачная плёнка | Z67: Технология / процесс
A68: PL-HIST-0067 | B68: 1891 | C68: год | D68: США | E68: Рочестер, Нью-Йорк | F68: Kodak / Eastman Company | G68: Kodak выводит первую daylight-loading camera: фотограф может перезаряжать плёнку без тёмной комнаты. | H68: Негатив-позитив | I68: Daylight-loading roll-film camera | J68: Рулонная фотография становится ещё удобнее: перезарядка перестаёт требовать полной темноты. | K68: Kodak camera 1888 and factory service model | L68: Pocket Kodak, Folding Pocket Kodak, Brownie and standard roll-film formats | M68: Главная линия | N68: 4 | O68: PL-007 | P68: SRC-042 | Q68: Kodak — Milestones | R68: https://www.kodak.com/en/company/page/milestones/ | S68: 5 | T68: Это не главный герой урока, но важный шаг удобства: фотограф получает больше самостоятельности. | U68: На карте: маленькая камера открывается на свету без тёмной комнаты. | V68: #PL007 #daylight-loading #roll-film #Kodak | X68: 43.1566, -77.6088 | Y68: Рулонная плёнка / дневная перезарядка | Z68: Технология / процесс
A69: PL-HIST-0068 | B69: 1900 | C69: год | D69: США | E69: Рочестер, Нью-Йорк | F69: Eastman Kodak / Brownie | G69: Камера Brownie делает рулонную фотографию ещё более дешёвой и доступной для массового пользователя. | H69: Негатив-позитив | I69: Kodak Brownie / mass snapshot photography | J69: Идея Kodak доводится до массового уровня: фотография становится повседневным занятием и семейной практикой. | K69: Kodak camera 1888 and roll-film service model | L69: PL-008: массовая любительская фотография, snapshot-культура и Brownie как социальный перелом | M69: Связь / переход | N69: 4 | O69: PL-007 | P69: SRC-043 | Q69: National Science and Media Museum — Kodak Gallery | R69: https://www.scienceandmediamuseum.org.uk/whats-on/kodak-gallery | S69: 5 | T69: Это мост к следующему уроку: Kodak сделал фотографию проще, Brownie сделает её по-настоящему массовой. | U69: От Kodak 1888 линия идёт к дешёвой коробочной камере Brownie и семейным снимкам. | V69: #PL007 #Brownie #snapshot #mass-photography #future-PL | X69: 43.1566, -77.6088 | Y69: Рулонная плёнка / массовая фотография | Z69: Связь / переход
A70: PL-HIST-0069 | B70: 1900 | C70: год | D70: США | E70: Рочестер, Нью-Йорк | F70: Eastman Kodak / Brownie | G70: Появляется первая камера Kodak Brownie — простая и недорогая коробочная roll-film камера для массового пользователя. | H70: Негатив-позитив | I70: Kodak Brownie / box roll-film camera | J70: Фотография становится дешёвой и доступной: теперь камера перестаёт быть только инструментом обеспеченных любителей и профессионалов. | K70: Kodak camera 1888 и сервисная модель обработки плёнки | L70: Snapshot-культура, семейные альбомы и массовая любительская фотография | M70: Главная линия | N70: 5 | O70: PL-008 | P70: SRC-044 | Q70: Science Museum Group — No. 1 Brownie Box Camera | R70: https://collection.sciencemuseumgroup.org.uk/objects/co8406729/no-1-brownie-box-camera | S70: 5 | T70: Флагман PL-008: Brownie — момент, когда фотография становится по-настоящему массовой бытовой практикой. | U70: На карте: из Рочестера расходятся линии к домам, семьям и любительским снимкам. | V70: #PL008 #Brownie #Kodak #snapshot #mass-photography | X70: 43.1566, -77.6088 | Y70: Brownie / доступная камера | Z70: Ключевой исторический узел | AA70: да
A71: PL-HIST-0070 | B71: 1900 | C71: год | D71: США | E71: Рочестер, Нью-Йорк | F71: Eastman Kodak | G71: Brownie продаётся по низкой цене и продвигается как камера, которой может пользоваться человек без фотографического опыта. | H71: Негатив-позитив | I71: Low-cost consumer camera | J71: Порог входа резко падает: фотография становится не только техникой, но и доступным хобби. | K71: Kodak 1888 упростил процесс, но оставался сравнительно дорогим | L71: Brownie расширяет аудиторию до детей, семей и среднего класса | M71: Распространение / коммерциализация | N71: 5 | O71: PL-008 | P71: SRC-046 | Q71: ACS — George Eastman, Kodak, and the Birth of Consumer Photography | R71: https://www.acs.org/education/whatischemistry/landmarks/eastman-kodak.html | S71: 5 | T71: Объяснить просто: Kodak сделал фотографию удобной, а Brownie сделал её дешёвой. | U71: Ценник рядом с маленькой коробочной камерой: фотография становится покупкой для обычной семьи. | V71: #PL008 #Brownie #affordable-camera #consumer-photography | X71: 43.1566, -77.6088 | Y71: Brownie / цена и массовый рынок | Z71: Распространение / коммерциализация
A72: PL-HIST-0071 | B72: 1900–1901 | C72: диапазон | D72: США / Великобритания | E72: Рочестер / массовая пресса | F72: Eastman Kodak / рекламные кампании Brownie | G72: Brownie продвигается через популярную прессу и визуальный образ персонажей Brownie, обращаясь к новой молодой и семейной аудитории. | H72: Негатив-позитив | I72: Brownie marketing / popular press | J72: Фотокамера становится не только устройством, но и массовым культурным продуктом с понятным образом и обещанием простоты. | K72: Kodak как бренд и сервис съёмки | L72: Brownie становится узнаваемой народной камерой | M72: Распространение / коммерциализация | N72: 4 | O72: PL-008 | P72: SRC-047 | Q72: National Science and Media Museum — B is for Brownie | R72: https://blog.scienceandmediamuseum.org.uk/a-z-photography-collection-b-is-for-brownie/ | S72: 5 | T72: Хороший сюжет для урока: массовая фотография победила не только химией и камерой, но и рекламой. | U72: Визуально: рекламный плакат Brownie, персонажи и маленькая камера как игрушка для всех. | V72: #PL008 #Brownie #advertising #popular-press #children | X72: 43.1566, -77.6088 | Y72: Brownie / детская аудитория и реклама | Z72: Распространение / коммерциализация
A73: PL-HIST-0072 | B73: 1901 | C73: год | D73: Великобритания | E73: Лондон | F73: Kodak Limited / No. 2 Brownie | G73: No. 2 Brownie использует 120 roll film — формат, который позже станет важным стандартом среднего формата. | H73: Негатив-позитив | I73: No. 2 Brownie / 120 roll film | J73: Массовая простая камера оказывается связана с форматом плёнки, который переживёт саму эпоху Brownie и останется важным для фотографии. | K73: Brownie No. 1 и массовая roll-film камера | L73: 120 film и среднеформатная фотография XX века | M73: Главная линия | N73: 4 | O73: PL-008 | P73: SRC-050 | Q73: Science Museum Group — No 2 Brownie Camera | R73: https://collection.sciencemuseumgroup.org.uk/objects/co8207799/no-2-brownie-camera | S73: 4 | T73: Не перегружать технически: важно показать, что массовая камера дала жизнь формату, который потом станет серьёзным фотографическим стандартом. | U73: Рядом с камерой — катушка 120 film, мост к среднему формату. | V73: #PL008 #No2Brownie #120film #medium-format | W73: Проверить отдельно формулировку «первый / introduced 120» по более сильному источнику; в текущем виде писать осторожно: «использует 120 roll film». | X73: 51.5074, -0.1278 | Y73: Brownie / 120 roll film | Z73: Технология / процесс
A74: PL-HIST-0073 | B74: 1900-е | C74: диапазон | D74: США / Великобритания | E74: распределённый процесс | F74: Любители фотографии / семьи | G74: Snapshot становится повседневной практикой: люди снимают прогулки, детей, поездки, праздники и частную жизнь. | H74: Печать / тиражирование | I74: Snapshot culture / family photography | J74: Фотография меняет социальную роль: она перестаёт быть только портретом или документом и становится способом сохранять личную память. | K74: Brownie делает камеру доступной широкому кругу людей | L74: Семейные альбомы и бытовая визуальная культура XX века | M74: Главная линия | N74: 5 | O74: PL-008 | P74: SRC-049 | Q74: National Gallery of Art — The Art of the American Snapshot, 1888–1978 | R74: https://www.nga.gov/exhibitions/art-american-snapshot-1888-1978-collection-robert-e-jackson | S74: 5 | T74: Ключевой смысл: фотография входит в дом и начинает фиксировать обычную жизнь, а не только важные события. | U74: На карте: от камеры появляются маленькие карточки-снимки семьи, поездки, дома. | V74: #PL008 #snapshot #family-album #vernacular-photography | Y74: Snapshot-культура / семейный альбом | Z74: Применение / жанр
A75: PL-HIST-0074 | B75: 1900-е | C75: диапазон | D75: США | E75: распределённый процесс | F75: Массовые любители фотографии | G75: Фотография становится занятием людей без профессиональной подготовки: важнее не техническое мастерство, а возможность сохранить момент. | H75: Печать / тиражирование | I75: Amateur snapshot photography | J75: В центр выходит не фотограф-профессионал, а обычный человек с камерой; рождается культура бытового снимка. | K75: Kodak/Brownie снижает технический барьер | L75: Фотография как личный дневник, семейная память и визуальный архив | M75: Главная линия | N75: 5 | O75: PL-008 | P75: SRC-039 | Q75: The Met — Kodak and the Rise of Amateur Photography | R75: https://www.metmuseum.org/essays/kodak-and-the-rise-of-amateur-photography | S75: 5 | T75: Объяснить просто: раньше фотография была делом специалиста; теперь обычный человек получает право нажать кнопку и сохранить свою жизнь. | U75: Иконка: человек без студии и лаборатории снимает повседневный момент. | V75: #PL008 #amateur-photography #snapshot #everyday-life | Y75: Snapshot-культура / любительская практика | Z75: Применение / жанр
A76: PL-HIST-0075 | B76: 1900-е | C76: диапазон | D76: США | E76: Рочестер, Нью-Йорк / потребительский рынок | F76: Eastman Kodak / фотолаборатории | G76: Сервисная модель Kodak продолжает освобождать пользователя от проявки и печати: съёмка становится проще, а обработка уходит в лабораторию. | H76: Печать / тиражирование | I76: Consumer processing service | J76: Массовая фотография требует не только камеры, но и инфраструктуры: плёнка, проявка, печать и возврат снимков становятся частью единой системы. | K76: Kodak service model 1888 | L76: Фотолаборатории, минилабы и массовая печать XX века | M76: Распространение / коммерциализация | N76: 4 | O76: PL-008 | P76: SRC-039 | Q76: The Met — Kodak and the Rise of Amateur Photography | R76: https://www.metmuseum.org/essays/kodak-and-the-rise-of-amateur-photography | S76: 5 | T76: Для PHOTO LAB это важный мост: массовая фотография сразу связана с лабораторией и печатью. | U76: Маршрут: пользователь снимает → лаборатория проявляет → отпечатки возвращаются. | V76: #PL008 #processing #photo-lab #Kodak-service #prints | X76: 43.1566, -77.6088 | Y76: Snapshot-культура / сервисная обработка | Z76: Распространение / коммерциализация
A77: PL-HIST-0076 | B77: 1900–1980-е | C77: диапазон | D77: США / Великобритания / глобально | E77: распределённый процесс | F77: Eastman Kodak / пользователи Brownie | G77: Линейка Brownie живёт десятилетиями и закрепляет образ простой камеры для всех. | H77: Негатив-позитив | I77: Brownie camera line | J77: Brownie становится не одиночной моделью, а длительной культурной идеей: простая камера, доступная широкой аудитории. | K77: Brownie No. 1 и ранняя массовая фотография | L77: Долгая традиция простых потребительских камер XX века | M77: Временная доминирующая линия | N77: 4 | O77: PL-008 | P77: SRC-047 | Q77: National Science and Media Museum — B is for Brownie | R77: https://blog.scienceandmediamuseum.org.uk/a-z-photography-collection-b-is-for-brownie/ | S77: 4 | T77: Важно: Brownie — это не только камера 1900 года, а символ народной фотографии на десятилетия. | U77: Таймлайн с разными поколениями Brownie как одной длинной народной линии. | V77: #PL008 #Brownie #camera-line #consumer-cameras | W77: Уточнить конкретные годы производства отдельных моделей Brownie при расширении темы. | Y77: Brownie / долгий жизненный цикл | Z77: Распространение / коммерциализация
A78: PL-HIST-0077 | B78: 1888–1978 | C78: диапазон | D78: США | E78: США / музейные коллекции | F78: Неизвестные фотографы / snapshot-архивы | G78: Массовые любительские снимки позже становятся историческим и культурным архивом повседневной жизни. | H78: Печать / тиражирование | I78: Vernacular photography / snapshot archive | J78: То, что начиналось как личные карточки «для себя», становится материалом для изучения общества, семьи, досуга и визуальной культуры. | K78: Kodak roll film и Brownie расширяют количество любительских снимков | L78: История vernacular photography и коллекционирование бытовых снимков | M78: Переходная технология | N78: 3 | O78: PL-008 | P78: SRC-049 | Q78: National Gallery of Art — The Art of the American Snapshot, 1888–1978 | R78: https://www.nga.gov/exhibitions/art-american-snapshot-1888-1978-collection-robert-e-jackson | S78: 5 | T78: Смысл для начинающего: даже обычный семейный снимок со временем может стать историческим документом. | U78: Коробка старых снимков превращается в музейный архив. | V78: #PL008 #vernacular #snapshot-archive #museum #everyday-history | Y78: Snapshot-культура / культурный архив | Z78: Применение / жанр
A79: PL-HIST-0078 | B79: 1913 / 1925 | C79: диапазон | D79: Германия | E79: Вецлар / Лейпциг | F79: Оскар Барнак / Leica | G79: После массовых box-камер следующий большой вопрос — как сделать камеру компактной, быстрой и качественной; к этому ведёт линия 35 мм и Leica. | H79: Негатив-позитив | I79: Bridge to 35mm miniature photography | J79: Фотография уже стала массовой, но следующий этап — сделать маленькую камеру серьёзным инструментом для живой съёмки. | K79: Brownie и snapshot-культура показывают силу простой камеры | L79: PL-009: 35 мм, Leica и новая мобильность фотографа | M79: Связь / переход | N79: 5 | O79: PL-008 | P79: SRC-051 | Q79: Smithsonian NMAH — Leica 35 mm 1(A) Camera | R79: https://americanhistory.si.edu/collections/object/nmah_834692 | S79: 5 | T79: Это мост к PL-009: после «камеры для всех» появится идея компактной камеры для быстрой и качественной фотографии. | U79: Линия от коробочной Brownie к маленькой 35-мм камере Leica. | V79: #PL008 #bridge #Leica #35mm #future-PL | W79: При заполнении PL-009 уточнить отдельно Ur-Leica 1913, Leica I 1925 и роль 35-мм кино-плёнки. | X79: 50.5619, 8.5044 | Y79: Brownie / мост к 35 мм | Z79: Связь / переход
A80: PL-HIST-0079 | B80: 1889 | C80: год | D80: США | E80: Рочестер, Нью-Йорк | F80: Джордж Истмен / Eastman Kodak | G80: Промышленная прозрачная рулонная плёнка Eastman создаёт гибкий носитель, из которого вскоре вырастет киноформат 35 мм. | H80: Негатив-позитив | I80: Transparent roll film | J80: Плёнка становится не только альтернативой стеклянной пластине, но и материалом для длинной последовательности кадров. | K80: Рулонная плёнка Kodak 1888–1889 | L80: Edison/Dickson use flexible film for motion-picture camera | M80: Связь / переход | N80: 5 | O80: PL-009 | P80: SRC-052 | Q80: Kodak — Motion Picture History | R80: https://www.kodak.com/en/company/page/motion-picture-history/ | S80: 5 | T80: Для PL-009 важно показать: 35 мм родился не сразу как фотоплёнка для фотоаппарата, а через кинематографический носитель. | U80: Рулон прозрачной плёнки превращается в длинную дорожку кадров. | V80: #PL009 #35mm #transparent-film #Eastman #cinema-roots | X80: 43.1566, -77.6088 | Y80: 35 мм / прозрачная рулонная плёнка | Z80: Связь / переход
A81: PL-HIST-0080 | B81: 1891 | C81: год | D81: США | E81: Вест-Ориндж, Нью-Джерси | F81: Томас Эдисон / Уильям К. Л. Диксон | G81: В лаборатории Эдисона разрабатываются Kinetograph и Kinetoscope; в патентной логике ширина плёнки фиксируется как 35 мм. | H81: Проекция / распространение | I81: Kinetograph / Kinetoscope 35 mm film | J81: 35 мм начинает работать как практический формат для записи и показа движущегося изображения. | K81: Прозрачная рулонная плёнка Eastman | L81: 35 мм закрепляется в кино как рабочий стандарт | M81: Главная линия | N81: 5 | O81: PL-009 | P81: SRC-053 | Q81: Library of Congress — Origins of Motion Pictures | R81: https://www.loc.gov/collections/edison-company-motion-pictures-and-sound-recordings/articles-and-essays/history-of-edison-motion-pictures/origins-of-motion-pictures/ | S81: 5 | T81: Объяснить аккуратно: это ещё не фотоаппарат Leica, а кинематографический стандарт, который позже будет переосмыслен фотографией. | U81: Лаборатория Эдисона: лента плёнки проходит через механизм с перфорацией. | V81: #PL009 #Edison #Dickson #Kinetograph #35mm | X81: 40.7987, -74.2390 | Y81: 35 мм / киноистоки | Z81: Технология / процесс
A82: PL-HIST-0081 | B82: 1890-е | C82: диапазон | D82: США | E82: Вест-Ориндж, Нью-Джерси | F82: Уильям К. Л. Диксон / Kodak | G82: Диксон использует прозрачную плёнку Kodak шириной 70 мм, разрезает её пополам до 35 мм и перфорирует для Edison Kinetoscope. | H82: Проекция / распространение | I82: 35 mm perforated motion-picture film | J82: Появляется физическая логика формата: узкая гибкая лента, перфорация, кадры, механическая протяжка. | K82: Transparent Kodak film | L82: International 35 mm motion-picture practice | M82: Главная линия | N82: 5 | O82: PL-009 | P82: SRC-054 | Q82: George Eastman Museum — Early Kodak transparent film | R82: https://www.eastman.org/two-rare-rolls-early-kodak-film-acquired-george-eastman-museum | S82: 5 | T82: Это красивый узел для карты: 70 мм делится пополам — и рождается 35-мм дорожка. | U82: 70-мм рулон плёнки разрезан на две 35-мм ленты с перфорацией. | V82: #PL009 #Dickson #Kodak #perforation #35mm-film | W82: Проверить формулировку периода: точный год разрезания 70 мм на 35 мм в разных источниках может отличаться. | X82: 40.7987, -74.2390 | Y82: 35 мм / ширина и перфорация | Z82: Ключевой исторический узел
A83: PL-HIST-0082 | B83: 1893–1894 | C83: диапазон | D83: США | E83: Вест-Ориндж / Нью-Йорк | F83: Edison Manufacturing Company / зрители Kinetoscope | G83: Kinetoscope показывает движущиеся изображения на 35-мм перфорированной плёнке и превращает формат в публичный медианоситель. | H83: Проекция / распространение | I83: 35 mm Kinetoscope viewing | J83: 35 мм становится не лабораторной пробой, а частью публичной визуальной культуры. | K83: Kinetograph and perforated 35 mm film | L83: Dominance of 35 mm motion-picture projection and production | M83: Главная линия / временная доминирующая линия | N83: 4 | O83: PL-009 | P83: SRC-055 | Q83: George Eastman Museum — Kinetoscope | R83: https://collections.eastman.org/objects/78087/kinetoscope | S83: 5 | T83: Новичку важно: до Leica 35 мм уже был массовым форматом движения и развлечения. | U83: Аппарат Kinetoscope с лентой 35 мм внутри и зрителем у окуляра. | V83: #PL009 #Kinetoscope #cinema #35mm #public-viewing | X83: 40.7128, -74.0060 | Y83: 35 мм / Kinetoscope | Z83: Распространение / коммерциализация
A84: PL-HIST-0083 | B84: 1908–1909 | C84: диапазон | D84: международный процесс | E84: США / Европа | F84: Киноиндустрия / MPPC / производители оборудования | G84: 35-мм киноплёнка с четырьмя перфорациями на кадр фактически закрепляется как международный производственный и прокатный стандарт. | H84: Проекция / распространение | I84: 35 mm motion-picture standard | J84: Стандартизация делает формат удобным для индустрии: камеры, проекторы, лаборатории и прокат начинают говорить на одном техническом языке. | K84: Edison/Dickson 35 mm practice | L84: 35 mm cine film becomes available for still-camera reinterpretation | M84: Главная линия / временная доминирующая линия | N84: 4 | O84: PL-009 | P84: SRC-056 | Q84: SMPTE Journal — The Origins of 35mm Film as a Standard | R84: https://journal.smpte.org/periodicals/SMPTE%20Journal/99/8/22/ | S84: 4 | T84: Это узел про стандарт: когда формат становится общим языком, его легче взять и переосмыслить в фотографии. | U84: Схема: камера → плёнка 35 мм → проектор → общий стандарт. | V84: #PL009 #35mm-standard #cinema #SMPTE #MPPC | W84: Проверить детали 1908–1909 и роль MPPC при финальной редакции лекции. | Y84: 35 мм / международный стандарт | Z84: Ключевой исторический узел
A85: PL-HIST-0084 | B85: 1913–1914 | C85: диапазон | D85: Германия | E85: Вецлар | F85: Оскар Барнак / Ernst Leitz | G85: Оскар Барнак создаёт прототип Ur-Leica: поворачивает 35-мм киноплёнку в горизонтальную ориентацию и получает кадр 24×36 мм. | H85: Негатив-позитив | I85: 24×36 mm still frame on 35 mm film | J85: Киноноситель становится фотографическим форматом: маленький негатив можно увеличить до полноценного отпечатка. | K85: 35 mm motion-picture standard | L85: Leica I and small-format photography | M85: Главная линия | N85: 5 | O85: PL-009 | P85: SRC-057 | Q85: Leica Timeline — 1914 | R85: https://timeline.leica-camera.com/en-US/years/1914 | S85: 5 | T85: Главная идея PL-009: не просто плёнка 35 мм, а поворот мышления — киноформат превращают в компактную фотографическую систему. | U85: 35-мм кинолента поворачивается горизонтально; появляется прямоугольник 24×36. | V85: #PL009 #Ur-Leica #Oskar-Barnack #24x36 #35mm | X85: 50.5619, 8.5044 | Y85: 35 мм / 24×36 | Z85: Ключевой исторический узел | AA85: да
A86: PL-HIST-0085 | B86: 1920 | C86: год | D86: Германия | E86: Вецлар | F86: Оскар Барнак | G86: Барнак снимает на прототип Leica наводнение в Вецларе; серия часто рассматривается как ранний пример 35-мм репортажной фотографии. | H86: Негатив-позитив | I86: 35 mm reportage series | J86: Компактная камера показывает свою силу: фотограф может быть ближе к событию и двигаться быстрее. | K86: Ur-Leica prototype and 24×36 format | L86: Small camera becomes tool for reportage and street photography | M86: Переходная технология | N86: 4 | O86: PL-009 | P86: SRC-058 | Q86: Leica Oskar Barnack Award — Oskar Barnack | R86: https://www.leica-oskar-barnack-award.com/en/information/oskar-barnack.html | S86: 5 | T86: Важно для storytelling: 35 мм меняет не только технику, но и поведение фотографа — он становится мобильным наблюдателем. | U86: Фотограф с маленькой камерой среди реального события, не в студии. | V86: #PL009 #reportage #Barnack #Wetzlar #35mm | X86: 50.5619, 8.5044 | Y86: 35 мм / репортажность | Z86: Применение / жанр
A87: PL-HIST-0086 | B87: 1924 / 1925 | C87: диапазон | D87: Германия | E87: Вецлар / Лейпциг | F87: Oskar Barnack / Ernst Leitz | G87: Leica 1(A), разработанная Барнаком, объявлена в 1924 году и продаётся с 1925 года; она популяризирует 35-мм фотографию. | H87: Оптические инструменты | I87: Leica 1(A) 35 mm camera | J87: 35 мм выходит из экспериментального прототипа в коммерческую фотографическую практику. | K87: Ur-Leica and 24×36 format | L87: Leica I as the next dedicated lesson PL-010 | M87: Главная линия | N87: 5 | O87: PL-009 | P87: SRC-059 | Q87: Smithsonian NMAH — Leica 35 mm 1(A) Camera | R87: https://americanhistory.si.edu/collections/object/nmah_834692 | S87: 5 | T87: Этот узел — мост к PL-010: в PL-009 объясняем формат, в PL-010 подробно разбираем Leica I. | U87: Маленькая Leica рядом с тяжёлой старой камерой: формат меняет масштаб фотографии. | V87: #PL009 #Leica #Leica1A #35mm #Barnack | X87: 51.3397, 12.3731 | Y87: 35 мм / коммерциализация Leica | Z87: Инструмент / устройство
A88: PL-HIST-0087 | B88: 1925 | C88: год | D88: Германия | E88: Лейпциг | F88: Ernst Leitz / Leica | G88: Leica I дебютирует на Лейпцигской весенней ярмарке как первая серийная 35-мм камера Leitz. | H88: Оптические инструменты | I88: Leica I serial production | J88: Компактная камера становится серьёзным фотографическим инструментом, а не игрушкой или лабораторной пробой. | K88: Commercial Leica 1(A) launch | L88: PL-010: Leica I and the new language of photography | M88: Переходная технология | N88: 5 | O88: PL-009 | P88: SRC-060 | Q88: Leica Timeline — 1925 | R88: https://timeline.leica-camera.com/en/years/1925 | S88: 5 | T88: Оставить как переход: это событие нужно не раскрывать полностью, а открыть дверь в PL-010. | U88: Ярмарочная витрина Leica I как вход в следующий урок. | V88: #PL009 #LeicaI #Leipzig #small-format #future-PL010 | W88: Не дублировать слишком подробно с PL-010: здесь только мост к следующему уроку. | X88: 51.3397, 12.3731 | Y88: 35 мм / мост к Leica I | Z88: Связь / переход
A89: PL-HIST-0088 | B89: 1934 | C89: год | D89: Германия | E89: Штутгарт | F89: Kodak AG / Kodak Retina | G89: Kodak Retina Type 117 становится первой камерой для дневной загрузки 135-картриджей, которые сделают 35 мм удобнее для широкой фотографии. | H89: Негатив-позитив | I89: 135 daylight-loading cartridge | J89: 35 мм получает бытовую форму: плёнку становится легче покупать, вставлять в камеру и использовать без тёмной комнаты. | K89: Leica and manually loaded 35 mm film | L89: 135 cartridge becomes dominant consumer still-film format | M89: Переходная технология | N89: 4 | O89: PL-009 | P89: SRC-061 | Q89: Science Museum Group — Kodak Retina Type 117 | R89: https://collection.sciencemuseumgroup.org.uk/objects/co8205056/kodak-retina-type-117-35mm-camera | S89: 5 | T89: Финальный смысл PL-009: формат победил не только из-за качества, но и из-за удобства системы. | U89: Открытый 135-картридж рядом с Kodak Retina и полоской 35-мм плёнки. | V89: #PL009 #135-film #Kodak-Retina #35mm #cartridge | X89: 48.7758, 9.1829 | Y89: 35 мм / 135 cartridge | Z89: Распространение / коммерциализация
A90: PL-HIST-0089 | B90: 1913–1914 | C90: диапазон | D90: Германия | E90: Вецлар | F90: Оскар Барнак / Ernst Leitz | G90: Оскар Барнак создаёт прототип Ur-Leica: компактную камеру под 35-мм киноплёнку, которая станет основой будущей Leica I. | H90: Оптические инструменты | I90: Ur-Leica prototype | J90: Идея 35 мм перестаёт быть только кинематографической: появляется замысел маленькой фотокамеры для серьёзной съёмки. | K90: 35-мм киноплёнка и кадр 24×36 | L90: Leica 0-Series and Leica I | M90: Переходная технология | N90: 5 | O90: PL-010 | P90: SRC-062 | Q90: Leica Camera — The History of the Leica I | R90: https://leica-camera.com/en-int/photography/100-years/the-history-of-the-leica-I | S90: 5 | T90: Для урока важно показать: Leica I родилась не из желания сделать игрушку, а из идеи мобильной серьёзной камеры. | U90: Маленький прототип на рабочем столе Барнака рядом с полоской 35-мм киноплёнки. | V90: #PL010 #Ur-Leica #Barnack #Wetzlar #35mm | X90: 50.5619, 8.5044 | Y90: Leica I / прототип | Z90: Инструмент / устройство
A91: PL-HIST-0090 | B91: 1923 | C91: год | D91: Германия | E91: Вецлар | F91: Оскар Барнак / Ernst Leitz | G91: После прототипов появляется проверочная серия Leica 0-Series: небольшая партия камер для испытаний перед коммерческим запуском. | H91: Оптические инструменты | I91: Leica 0-Series | J91: Идея маленькой 35-мм камеры проходит практическую проверку: её нужно не просто изобрести, а сделать пригодной для реальных фотографов. | K91: Ur-Leica prototype | L91: Decision to enter serial production | M91: Переходная технология | N91: 4 | O91: PL-010 | P91: SRC-062 | Q91: Leica Camera — The History of the Leica I | R91: https://leica-camera.com/en-int/photography/100-years/the-history-of-the-leica-I | S91: 5 | T91: Хороший storytelling-узел: между прототипом и рынком всегда есть испытание, сомнение и проверка. | U91: Небольшая партия камер Leica 0-Series на столе в мастерской Leitz. | V91: #PL010 #Leica0 #preproduction #Leitz #Barnack | W91: Проверить точное количество камер 0-Series в финальной лекции: источники обычно указывают малую проверочную серию, но формулировки различаются. | X91: 50.5619, 8.5044 | Y91: Leica I / проверочная серия | Z91: Связь / переход
A92: PL-HIST-0091 | B92: конец 1924 | C92: точная дата | D92: Германия | E92: Вецлар | F92: Ernst Leitz II / Ernst Leitz Werke | G92: Первая серийная версия Leica I официально входит в производство в конце 1924 года, опираясь на опыт Leica 0-Series. | H92: Оптические инструменты | I92: Leica I serial production begins | J92: Leica перестаёт быть лабораторным экспериментом и становится промышленным изделием. | K92: Leica 0-Series tests | L92: Public presentation at Leipzig Spring Fair 1925 | M92: Главная линия | N92: 5 | O92: PL-010 | P92: SRC-062 | Q92: Leica Camera — The History of the Leica I | R92: https://leica-camera.com/en-int/photography/100-years/the-history-of-the-leica-I | S92: 5 | T92: Объяснить просто: революция начинается не в момент идеи, а когда идею удалось произвести серийно. | U92: Фабричная сборка маленьких Leica I в Вецларе, рядом детали корпуса и объектив. | V92: #PL010 #LeicaI #serial-production #Leitz | X92: 50.5619, 8.5044 | Y92: Leica I / начало производства | Z92: Распространение / коммерциализация
A93: PL-HIST-0092 | B93: 1925 | C93: год | D93: Германия | E93: Лейпциг | F93: Ernst Leitz / Leica | G93: Leica I представлена публике на Лейпцигской весенней ярмарке как первая серийная 35-мм камера Leitz. | H93: Оптические инструменты | I93: Leica I at Leipzig Spring Fair | J93: 35 мм получает публичный коммерческий вход в фотографию: маленькая камера становится реальным продуктом. | K93: Serial production begins at Leitz | L93: Compact 35 mm photography spreads | M93: Главная линия | N93: 5 | O93: PL-010 | P93: SRC-063 | Q93: Leica Camera — 100 Years of Leica: Witness to a Century | R93: https://leica-camera.com/en-GB/press/100-years-leica-witness-century-1925-2025-1 | S93: 5 | T93: Это главный исторический момент урока: Leica I выходит к публике и меняет представление о серьёзной камере. | U93: Витрина Leica I на ярмарке в Лейпциге; маленькая камера среди больших фотоаппаратов эпохи. | V93: #PL010 #LeicaI #Leipzig #1925 #35mm-camera | X93: 51.3397, 12.3731 | Y93: Leica I / публичный дебют | Z93: Ключевой исторический узел | AA93: да
A94: PL-HIST-0093 | B94: 1925 | C94: год | D94: Германия | E94: Вецлар | F94: Oskar Barnack / Ernst Leitz | G94: Leica 1(A), разработанная Барнаком, становится первой коммерчески доступной Leica 35-мм камерой и быстро популяризирует 35-мм фотографию. | H94: Оптические инструменты | I94: Leica 1(A) 35 mm camera | J94: Компактность становится серьёзным фотографическим преимуществом: камера теперь может быть постоянно с фотографом. | K94: Leica I public launch | L94: New mobile visual practice | M94: Главная линия | N94: 5 | O94: PL-010 | P94: SRC-064 | Q94: Smithsonian NMAH — Leica 35 mm 1(A) Camera | R94: https://americanhistory.si.edu/collections/object/nmah_834692 | S94: 5 | T94: Новичку важно понять: Leica I — это не просто новая модель, а изменение поведения фотографа. | U94: Маленькая Leica I в руке фотографа рядом с большой складной камерой как контраст старого и нового. | V94: #PL010 #Leica1A #compact-camera #35mm #Barnack | X94: 50.5619, 8.5044 | Y94: Leica I / компактная камера | Z94: Инструмент / устройство
A95: PL-HIST-0094 | B95: 1925 | C95: год | D95: Германия | E95: Вецлар | F95: Макс Берек / Leitz | G95: Первые объективы Leica разрабатывает Макс Берек: 50 мм f/3.5 Anastigmat / Elmax, затем Elmar, чтобы маленький негатив можно было качественно увеличивать. | H95: Оптические инструменты | I95: Leica Anastigmat / Elmax / Elmar 50 mm f/3.5 | J95: Малый формат требует сильной оптики: качество объектива становится условием идеи «маленький негатив — большой отпечаток». | K95: 24×36 mm small negative | L95: Leica becomes practical system for enlargement and printing | M95: Главная линия | N95: 5 | O95: PL-010 | P95: SRC-065 | Q95: Leica Camera — Understanding Leica Lenses | R95: https://leica-camera.com/en-int/photography/understanding-leica-lenses | S95: 5 | T95: Это мост к будущим урокам про объективы: формат победил не один, ему понадобилась точная оптика. | U95: Схема: маленький негатив 24×36 → объектив Elmar → увеличенный отпечаток. | V95: #PL010 #MaxBerek #Elmar #Leica-lens #small-negative | W95: Уточнить в финальном тексте различие Anastigmat / Elmax / Elmar, чтобы не смешать ранние версии объектива. | X95: 50.5619, 8.5044 | Y95: Leica I / оптика и Elmar | Z95: Технология / процесс
A96: PL-HIST-0095 | B96: 1925–1930 | C96: диапазон | D96: Германия | E96: Вецлар | F96: Ernst Leitz Werke / пользователи Leica | G96: За 1925–1930 годы Leica I выпускается десятками тысяч экземпляров в разных вариантах и закрепляет 35-мм компактную камеру как рабочий фотографический инструмент. | H96: Негатив-позитив | I96: Leica I mass adoption | J96: 35 мм перестаёт быть нишевым экспериментом и становится устойчивой практикой съёмки. | K96: Leica I launch | L96: Global 35 mm compact camera standard | M96: Распространение / коммерциализация | N96: 5 | O96: PL-010 | P96: SRC-062 | Q96: Leica Camera — The History of the Leica I | R96: https://leica-camera.com/en-int/photography/100-years/the-history-of-the-leica-I | S96: 5 | T96: Не перегружать цифрами, но показать масштаб: камера стала не редкостью, а узнаваемым инструментом. | U96: Ряд Leica I на производственной полке, рядом отметка 1925–1930. | V96: #PL010 #LeicaI #mass-production #35mm-standard | X96: 50.5619, 8.5044 | Y96: Leica I / массовое принятие | Z96: Распространение / коммерциализация
A97: PL-HIST-0096 | B97: 1920-е–1930-е | C97: диапазон | D97: Европа / США | E97: распределённый процесс | F97: Фотографы нового поколения | G97: Компактная, быстрая и мобильная Leica I помогает сформировать более интимный, спонтанный визуальный язык — основу репортажа и уличной фотографии. | H97: Оптические инструменты | I97: Mobile 35 mm visual language | J97: Фотограф становится менее заметным и быстрее реагирует на жизнь: камера начинает следовать за событием, а не заставлять событие приходить в студию. | K97: Leica I mass adoption | L97: Rangefinder and reportage traditions | M97: Главная линия | N97: 5 | O97: PL-010 | P97: SRC-062 | Q97: Leica Camera — The History of the Leica I | R97: https://leica-camera.com/en-int/photography/100-years/the-history-of-the-leica-I | S97: 5 | T97: Смысл PL-010: Leica изменила не только размер камеры, но и способ видеть — ближе, быстрее, тише. | U97: Фотограф с маленькой камерой среди городской жизни; люди не позируют, момент происходит сам. | V97: #PL010 #reportage #street-photography #mobile-camera #visual-language | Y97: Leica I / новая визуальная практика | Z97: Применение / жанр
A98: PL-HIST-0097 | B98: 1930 | C98: год | D98: Германия | E98: Вецлар | F98: Ernst Leitz Werke | G98: Leica I(C) вводит сменные объективы; к концу 1930 года появляется стандартизированный крепёж, позволяющий использовать объективы с разными камерами Leica 1(C). | H98: Оптические инструменты | I98: Leica I(C) interchangeable lenses | J98: Leica превращается из отдельной камеры в систему: корпус, объективы и аксессуары начинают развиваться вместе. | K98: Leica I fixed-lens camera | L98: Leica system and rangefinder cameras | M98: Связь / переход | N98: 4 | O98: PL-010 | P98: SRC-067 | Q98: Smithsonian NMAH — Leica 1(C) | R98: https://americanhistory.si.edu/collections/object/nmah_1145349 | S98: 5 | T98: Это не центральный узел PL-010, а мост: после Leica I важной становится идея системы. | U98: Корпус Leica I(C) и три объектива рядом: 50 мм, широкоугольный и телеобъектив. | V98: #PL010 #LeicaIC #interchangeable-lenses #Leica-system | W98: Проверить терминологию крепления: в источниках встречаются screw mount / standardized mount; не называть это байонетом в финальном русском тексте. | X98: 50.5619, 8.5044 | Y98: Leica I / сменные объективы | Z98: Связь / переход
A99: PL-HIST-0098 | B99: 1932 | C99: год | D99: Германия | E99: Вецлар | F99: Ernst Leitz Werke | G99: Leica II становится первой Leica со встроенным дальномером, продолжая линию малой 35-мм камеры в сторону точной быстрой фокусировки. | H99: Оптические инструменты | I99: Leica II built-in rangefinder | J99: Следующий шаг после компактности — скорость и точность наведения: Leica формирует основу дальномерной культуры съёмки. | K99: Leica I and Leica system | L99: Future rangefinder photography and Leica M lineage | M99: Связь / переход | N99: 4 | O99: PL-010 | P99: SRC-068 | Q99: Leica Timeline — 1932 | R99: https://timeline.leica-camera.com/en-US/years/1932 | S99: 5 | T99: Финальный мост урока: PL-010 завершает Модуль 1, но открывает будущие темы про камеры, дальномер и объективы. | U99: Leica II рядом с Leica I: появляется дальномер как следующий слой управления камерой. | V99: #PL010 #LeicaII #rangefinder #future-lessons #Leica-system | X99: 50.5619, 8.5044 | Y99: Leica I / мост к дальномерной системе | Z99: Связь / переход
A100: PL-HIST-0099 | B100: 1889 | C100: год | D100: США | E100: Рочестер, Нью-Йорк | F100: Eastman Dry Plate and Film Company / Kodak | G100: Kodak Transparent Film появляется как гибкий прозрачный фотоматериал для Kodak camera: светочувствительный слой теперь держится не на стекле, а на тонкой прозрачной основе. | H100: Негатив-позитив | I100: Transparent flexible photographic film | J100: Фотоплёнка становится самостоятельным материалом: гибкая основа + светочувствительная эмульсия заменяют тяжёлую стеклянную пластину. | K100: Рулонная бумажная плёнка Kodak и сухие пластины | L100: Понимание структуры плёнки: основа, эмульсия, защитные и служебные слои | M100: Главная линия | N100: 5 | O100: PL-011 | P100: SRC-069 | Q100: George Eastman Museum — Early Kodak Film 1888/1889 | R100: https://www.eastman.org/two-rare-rolls-early-kodak-film-acquired-george-eastman-museum | S100: 5 | T100: Начать PL-011 можно с простой мысли: плёнка — это не «магическая лента», а светочувствительный материал на гибкой основе. | U100: Схема-слой: прозрачная лента, сверху тонкая эмульсия; рядом стеклянная пластина как прошлый этап. | V100: #PL011 #film-material #transparent-film #Kodak #Eastman | X100: 43.1566, -77.6088 | Y100: Плёнка как материал / прозрачная основа | Z100: Ключевой исторический узел | AA100: да
...

Sheet 02_Branches
A1: Ветка | B1: Что включает | C1: Для каких уроков | D1: Визуальный цвет/код | E1: Комментарий
A2: Оптика / камера-обскура | B2: свет, тёмная комната, pinhole, линзы | C2: PL-001 | D2: синий | E2: Это предпосылка фотографии, не сама фотография.
A3: Оптические инструменты | B3: camera lucida, stereoscope, portable camera obscura, compact 35mm cameras, Leica I, Leica system, rangefinder lineage, SLR, TLR, compact point-and-shoot, средний формат, большой формат, view camera, устройство плёночной камеры, выбор первой камеры, авторская роль камеры, объектив, элементы объектива, байонет, диафрагма, фокусное расстояние, угол зрения, широкий угол, нормальный 50 мм, портретный объектив, телеобъектив, светосила, диафрагма, базовая экспозиция, диафрагма как окно, выдержка как время, ISO как чувствительность, экспозиционный треугольник, стопы света | C3: PL-001 / PL-009 / PL-010 / PL-021–PL-039 / PL-041–PL-046 / будущие PL | D3: голубой | E3: Оптическая и камерная линия: от оптических предпосылок к устройству камеры, объективам, типам фокусных расстояний и управлению экспозицией через диафрагму, выдержку, ISO и стопы света.
A4: Фотохимия | B4: серебряные соли, желатиновые эмульсии, скрытое изображение, проявление, чувствительность, ISO / film speed, EI, push/pull, спектральная чувствительность, зерно, цветные слои, color couplers, C-41, E-6, reversal-процесс, экспозиционная широта, сенситометрия / характеристическая кривая | C4: PL-002 / PL-006 / PL-011 / PL-012 / PL-015 / PL-016 / PL-017 / PL-018 / PL-019 / PL-020 | D4: жёлтый | E4: Химическая половина рождения фотографии: от серебряного изображения к чувствительности, зерну, цвету и экспозиционному диапазону материала.
A5: Гелиография | B5: Ньепс, битум, первое сохранившееся изображение | C5: PL-002 | D5: золотой | E5: Путь к постоянному изображению.
A6: Дагеротип | B6: прямой позитив на серебряной пластине | C6: PL-003 | D6: серебряный | E6: Резкость и публичный эффект, но уникальный экземпляр.
A7: Фотогенный рисунок / фотограмма | B7: контактные изображения объектов на бумаге | C7: PL-004 | D7: зелёный | E7: Британская линия Тальбота.
A8: Печать / тиражирование | B8: salt print, albumen print, gelatin silver print, POP/DOP, chromogenic print, фотокнига, лабораторная и сервисная печать, цветная печать с негатива, влияние зерна и экспозиции на скан/отпечаток, контактная печать, крупный негатив | C8: PL-004 / PL-013 / PL-014 / PL-015 / PL-016 / PL-019 / PL-020 / PL-028 | D8: оранжевый | E8: Ветка распространения изображений: от единичного отпечатка к массовому фотосервису, авторскому управлению финальной фактурой и контактному отпечатку крупного негатива.
A9: Печать / тиражирование | B9: salt print, albumen print, gelatin silver print, POP/DOP, chromogenic print, фотокнига, лабораторная и сервисная печать, цветная печать с негатива, влияние зерна и экспозиции на скан/отпечаток | C9: PL-004 / PL-013 / PL-014 / PL-015 / PL-016 / PL-019 / PL-020 | D9: оранжевый | E9: Ветка распространения изображений: от единичного отпечатка к массовому фотосервису и авторскому управлению финальной фактурой.
A10: Печать / тиражирование | B10: salt print, albumen print, gelatin silver print, POP/DOP, chromogenic print, фотокнига, лабораторная и сервисная печать, цветная печать с негатива | C10: PL-004 / PL-013 / PL-014 / PL-015 / PL-016 | D10: оранжевый | E10: Ветка распространения изображений: от единичного отпечатка к массовому фотосервису.
A11: Уникальный позитив | B11: ранний цвет, Autochrome, Kodachrome, Kodacolor, Ektachrome, цветная негативная и слайдовая плёнка, chromogenic print, C-41, E-6, узкая широта слайдового позитива | C11: PL-014 / PL-016 / PL-017 / PL-020 / будущие PL | D11: серый | E11: Важные, но технологически ограниченные ветки; слайдовая прозрачность особенно хорошо показывает цену ошибки экспозиции.
A12: Цвет | B12: цветные негативы, слайды, прозрачности, projected positive, Kodachrome, Ektachrome, EKTAR, EKTACOLOR, цветное зерно/красители, широта цветного негатива и слайда | C12: PL-016 / PL-017 / PL-019 / PL-020 / будущие PL | D12: радужный | E12: Цветная фотография как отдельная технологическая и визуальная линия: материал, проявка, просмотр, печать и экспозиционный допуск.
... A14: Проекция / распространение | B14: lantern slides, публичный показ | C14: будущие PL | D14: бирюзовый | E14: Мост к обучению, лекциям, презентациям.

Sheet 03_Lessons_Map
A1: Урок | B1: Главная тема | C1: Исторические узлы | D1: Что должен понять новичок | E1: Статус | F1: Ссылка на урок (Telegram)
A2: PL-001 | B2: Камера-обскура и оптика | C2: PL-HIST-0001…0008, 0013, 0028 | D2: Свет умеет строить изображение, но ещё не сохраняет его. | E2: основа готова | F2: https://t.me/photolab_vf_pro/4/40
A3: PL-002 | B3: Ньепс и первая фиксация | C3: PL-HIST-0009…0016 | D3: Недостаточно увидеть изображение — его нужно зафиксировать. | E3: основа готова | F3: https://t.me/photolab_vf_pro/4/54
A4: PL-003 | B4: Дагеротип | C4: PL-HIST-0017…0023, 0027 | D4: Фотография стала публичной, резкой и убедительной, но изображение было уникальным. | E4: основа готова | F4: https://t.me/photolab_vf_pro/4/59
A5: PL-004 | B5: Тальбот, калотип, негатив-позитив | C5: PL-HIST-0019…0026, 0029…0035 | D5: Идея копирования победила: один негатив может дать много отпечатков. | E5: основа готова | F5: https://t.me/photolab_vf_pro/4/64
A6: PL-005 | B6: Мокрый коллодий | C6: PL-HIST-0041…0048 | D6: Резкость дагеротипа и тираж калотипа встретились на стеклянной влажной пластине. | E6: основа готова | F6: https://t.me/photolab_vf_pro/4/69
A7: PL-006 | B7: Сухие желатиновые пластины | C7: PL-HIST-0049…0058 | D7: Фотография освобождается от немедленной полевой химии: пластину можно купить, хранить, экспонировать и проявлять позже. | E7: основа заполнена | F7: https://t.me/photolab_vf_pro/4/75
A8: PL-007 | B8: Рулонная плёнка и Kodak | C8: PL-HIST-0059…0068 | D8: Фотография освобождается от стеклянной пластины: рулонный носитель, Kodak и сервис обработки делают съёмку проще и ближе к массовому пользователю. | E8: основа заполнена | F8: https://t.me/photolab_vf_pro/4/105
A9: PL-008 | B9: Brownie и snapshot-культура | C9: PL-HIST-0069…0078 | D9: Фотография становится дешёвой и повседневной: обычные люди начинают снимать семью, поездки, детей и частную жизнь. | E9: основа заполнена | F9: https://t.me/photolab_vf_pro/4/110
A10: PL-009 | B10: 35 мм | C10: PL-HIST-0079…0088 | D10: 35 мм родился в кино, но стал языком компактной фотографии: киноплёнка превратилась в маленький кадр 24×36 и открыла путь Leica. | E10: основа заполнена | F10: https://t.me/photolab_vf_pro/4/118
A11: PL-010 | B11: Leica I | C11: PL-HIST-0089…0098 | D11: Leica I сделала 35 мм не просто форматом плёнки, а языком мобильной фотографии: маленькая камера стала серьёзным инструментом репортажа, улицы и повседневного наблюдения. | E11: основа заполнена | F11: https://t.me/photolab_vf_pro/4/131
A12: PL-011 | B12: Плёнка как светочувствительный материал | C12: PL-HIST-0099…0109 | D12: Плёнка — это не просто катушка, а многослойный светочувствительный материал: гибкая основа, эмульсия, серебряные соли, скрытое изображение и служебные слои. | E12: основа заполнена | F12: https://t.me/photolab_vf_pro/4/145
... A47: PL-046 | B47: Стопы света | C47: PL-HIST-0473…0483 | D47: Стопы света — общий язык экспозиции: каждый полный стоп добавляет или убирает свет в два раза через диафрагму, выдержку, ISO, фильтр или экспокоррекцию. | E47: основа заполнена | F47: https://t.me/photolab_vf_pro
A48: будущие PL | B48: Расширение после PL-046 | C48: PL-047 — недодержка; PL-048 — передержка; PL-049 — экспонометр; PL-050 — Sunny 16 | D48: После языка стопов курс переходит к ошибкам и измерению экспозиции: недодержка, передержка, экспонометр и солнечное правило. | E48: планируется

Sheet 04_Sources
A1: Источник ID | B1: Название | C1: URL | D1: Используется для | E1: Примечание
A2: SRC-001 | B2: AramcoWorld — Ibn al-Haytham: Testing is Believing | C2: https://www.aramcoworld.com/en/articles/2023/ibn-al-haytham-testing-is-believing | D2: Ибн аль-Хайсам, камера-обскура, прямолинейное распространение света | E2: вводный источник
A3: SRC-002 | B3: IMSS / Museo Galileo — Camera Obscura | C3: https://redi.imss.fi.it/inventions/index.php/Camera_Obscura | D3: Cardano, Della Porta, линза в камере-обскуре | E3: музейный образовательный источник
A4: SRC-003 | B4: Max Planck Institute — Camera Obscura PDF | C4: https://www.mpiwg-berlin.mpg.de/sites/default/files/Preprints/P307.pdf | D4: Kepler, термин camera obscura, развитие оптических приборов | E4: академический PDF
A5: SRC-004 | B5: Public Domain Review — Johann Zahn's Oculus Artificialis | C5: https://publicdomainreview.org/collection/images-from-johann-zahn-s-oculus-artificialis-1685 | D5: Johann Zahn, portable camera obscura | E5: источник по историческим изображениям
A6: SRC-005 | B6: Swiss Camera Museum — Johann Heinrich Schulze | C6: https://www.cameramuseum.ch/en/discover/permanent-exhibition/the-origins-of-photography/the-precursors-johann-heinrich-schulze/ | D6: Schulze, светочувствительность серебряных солей | E6: музейный источник
A7: SRC-006 | B7: Science History Institute — Silver and Sunlight | C7: https://www.sciencehistory.org/stories/magazine/silver-and-sunlight/ | D7: Scheele, silver chloride, ammonia | E7: научно-исторический источник
A8: SRC-007 | B8: Swiss Camera Museum — Thomas Wedgwood | C8: https://www.cameramuseum.ch/en/discover/permanent-exhibition/the-origins-of-photography/the-precursors-thomas-wedgwood/ | D8: Wedgwood, silver nitrate, early camera obscura attempts | E8: музейный источник
A9: SRC-008 | B9: Bodleian — Talbot Catalogue: Photogenic Drawing | C9: https://talbot.bodleian.ox.ac.uk/2017/02/17/an-account-of-the-processes-employed-in-photogenic-drawing/ | D9: Talbot, Wedgwood/Davy, photogenic drawing | E9: архивный/исследовательский источник
A10: SRC-009 | B10: Smithsonian NMAH — Camera Lucida | C10: https://americanhistory.si.edu/collections/object/nmah_1184286 | D10: Wollaston, Camera Lucida, 1806/1807 | E10: музейная карточка предмета
A11: SRC-010 | B11: Harry Ransom Center — The Niépce Heliograph | C11: https://www.hrc.utexas.edu/niepce-heliograph/ | D11: Niépce, View from the Window at Le Gras, heliography | E11: ключевой источник
A12: SRC-011 | B12: Maison Nicéphore Niépce — First experiments | C12: https://bicentennial-of-photography.org/niepce-and-the-invention-of-photography-niepce-s-first-experiments/ | D12: Niépce 1816, исчезающие negative images | E12: музей/юбилейный проект
... A317: SRC-315 | B317: FastRawViewer — The Unbearable Lightness of Mystic "Exposure" Triangle | C317: https://www.fastrawviewer.com/blog/mystic-exposure-triangle | D317: PL-045: critique of exposure triangle model, ISO invariance | E317: проверка технического факта, замена дубля PL-HIST-0462

Sheet 06_Lists
A1: Точность даты | B1: Статус ветки | C1: Урок | D1: Ветка | E1: Важность | F1: Уверенность | G1: Тип узла | H1: Подветка (детали)
A2: точная дата | B2: Временная доминирующая линия | C2: PL-001 | D2: Оптика / камера-обскура | E2: 1 | F2: 1 | G2: Фундаментальная предпосылка | H2: Оптика / терминология
A3: год | B3: Главная линия | C3: PL-002 | D3: Оптические инструменты | E3: 2 | F3: 2 | G3: Технология / процесс | H3: Оптика / камера
A4: примерно | B4: Главная линия / временная доминирующая линия | C4: PL-003 | D4: Фотохимия | E4: 3 | F4: 3 | G4: Инструмент / устройство | H4: Оптические инструменты / 3D
A5: диапазон | B5: Исторически важная ограниченная ветка | C5: PL-004 | D5: Гелиография | E5: 4 | F5: 4 | G5: Публикация / объявление | H5: Фотохимия / фиксация
A6: спорно/уточнить | B6: Исторически важная ограниченная ветка / художественное возрождение | C6: PL-005 | D6: Дагеротип | E6: 5 | F6: 5 | G6: Терминология / язык | H6: Фотохимия / первая фиксация
B7: Оптическая предпосылка | C7: PL-006 | D7: Фотогенный рисунок / фотограмма | G7: Связь / переход | H7: Фотохимия / публикация
B8: Переходная технология | C8: PL-007 | D8: Негатив-позитив | G8: Тиражирование / публикация | H8: Фотохимия / первая фиксация
B9: Переходная технология / художественное возрождение | C9: PL-008 | D9: Фиксаж / терминология | G9: Распространение / коммерциализация | H9: Первая фиксация / проблема постоянства
B10: Тупиковая / не получила развития | C10: PL-009 | D10: Печать / тиражирование | G10: Научное применение / пример | H10: Гелиография / первая сохранившаяся фотография
B11: Оптическая предпосылка | C11: PL-010 | D11: Мокрый коллодий | G11: Применение / жанр | H11: Передача идеи / развитие процесса
B12: Главная линия / ранний связанный дальномер | C12: PL-011 | D12: Уникальный позитив | G12: Ключевой исторический узел | H12: Дагеротип / публичное объявление
B13: Главная линия | C13: PL-012 | D13: Цвет | H13: Дагеротип / распространение
B14: Терминология / язык | C14: PL-013 | D14: Проекция / распространение | H14: Фотогенный рисунок / публикация
B15: Распространение / коммерциализация | C15: PL-014 | H15: Негатив-позитив / проявление
B16: Главная линия / пользовательское удобство | C16: PL-015 | H16: Научная фотография
B17: Применение / жанр | C17: PL-016 | H17: Цианотипия
B18: Связь / переход | C18: PL-017 | H18: Фотокнига / научная документация
B19: Главная линия / экспозиционный контроль | C19: PL-018 | H19: Фотокнига / тиражирование
B20: Главная линия / профессиональная система | C20: PL-019 | H20: Научная / медицинская фотография
B21: Главная линия / автоматизация SLR | C21: PL-020 | H21: Мокрый коллодий / распространение
B22: Главная линия / компактность | C22: PL-021 | H22: Мокрый коллодий / химия
B23: Главная линия / автофокусный компакт | C23: PL-022 | H23: Мокрый коллодий / камера
B24: Главная линия / автоматический compact | C24: PL-023 | H24: Уникальный позитив / мокрый коллодий
B25: Главная линия / премиальный компакт | C25: PL-024 | H25: Мокрый коллодий + печать
B26: Главная линия / потребительская автоматизация | C26: PL-025 | H26: Уникальный позитив / массовый портрет
... B48: Главная линия / точка съёмки | C48: будущие PL | H48: Brownie / цена и массовый рынок
B49: Главная линия / авторская ответственность | H49: Brownie / детская аудитория и реклама
B50: Главная линия / авторская работа | H50: Brownie / 120 roll film
B51: Главная линия / оптический принцип | H51: Snapshot-культура / семейный альбом
B52: Главная линия / фокусировка | H52: Snapshot-культура / любительская практика
B53: Главная линия / световой контроль | H53: Snapshot-культура / сервисная обработка
B54: Главная линия / угол зрения | H54: Brownie / долгий жизненный цикл
B55: Главная линия / тип объектива | H55: Snapshot-культура / культурный архив
B56: Главная линия / светосила | H56: Brownie / мост к 35 мм
B57: Главная линия / оптическая коррекция | H57: 35 мм / прозрачная рулонная плёнка
B58: Главная линия / просветление | H58: 35 мм / киноистоки
B59: Главная линия / оптическая схема | H59: 35 мм / ширина и перфорация
B60: Главная линия / механическая точность | H60: 35 мм / Kinetoscope
... B76: Главная линия / практическая характеристика | H76: Leica I / мост к дальномерной системе
H77: Плёнка как материал / прозрачная основа
H78: Плёнка как материал / нитратная основа
H79: Плёнка как материал / промышленное производство основы
H80: Плёнка как материал / механическая стабильность
H81: Плёнка как материал / safety film
H82: Плёнка как материал / ацетатная основа и хранение
H83: Плёнка как материал / структура слоя
H84: Плёнка как материал / серебряные соли и желатин
H85: Плёнка как материал / скрытое изображение и обработка
H86: Плёнка как материал / чувствительность и зерно
H87: Плёнка как материал / защитные и служебные слои
H88: Эмульсия / желатино-бромидный слой
... H400: Стопы света / итог и мост

Sheet 00_README
A1: PHOTO LAB — History Map Master v0.20
A2: Назначение | B2: Исследовательская база для будущей интерактивной карты развития фотографии: география + время + ветки технологий + привязка к урокам.
A3: Охват v0.17 | B3: От оптических предпосылок камеры-обскуры до Leica I, полный Модуль 2 о плёнке, Модуль 3 до PL-030, Модуль 4 до PL-039; Модуль 5 заполнен PL-041–PL-046. PL-040 пока оставлен отдельным будущим заполнением.
A4: Принцип | B4: Каждый факт должен отвечать на 5 вопросов: что произошло, где, кто связан, почему важно, чем подтверждено.
A5: Как пользоваться | B5: Фильтровать лист 01_Master_Facts по уроку, ветке развития, статусу ветки, типу узла, стране или уровню уверенности.
A6: Важно | B6: Поля «Проверить позже» и «Уверенность 1–5» оставлены специально: спорные даты и слабые источники не должны попадать в финальную карту без доработки.
A7: Правило веток | B7: Колонка H «Ветка развития» должна содержать только крупные ветки из листа 02_Branches. PL-024–PL-028 остаются внутри ветки «Оптические инструменты», кроме отдельных узлов печати/фотохимии для большого формата.
A8: Правило подветок | B8: Детализация хранится в колонке Y «Подветка (детали)»: дальномер, SLR, compact, средний формат, большой формат, view camera, подвижки и т.д. Это позволяет карте фильтровать крупно и подробно одновременно.
A9: Правило типа узла | B9: Тип узла = назначение факта на карте: технология, предпосылка, инструмент, публикация, терминология, применение, распространение, связь/переход и т.п.
A10: Единственный источник истины по урокам | B10: Для фильтра «по уроку» использовать только колонку «Привязка к уроку» в 01_Master_Facts. Диапазоны в 03_Lessons_Map — нарративные, не строгие множества, и могут пересекаться между уроками.
A11: Что изменено в v0.2.1 | B11: Исправлены формулы Dashboard с безопасными ссылками на листы, убрана остаточная строка «Цианотипия», нормализованы выпадающие списки, добавлена колонка «Тип узла», подготовлена строка PL-006.
A12: Что изменено в v0.3 | B12: Заполнен PL-006: добавлены PL-HIST-0049…0058 по сухим желатиновым пластинам, добавлены источники SRC-027…SRC-034, обновлены 02_Branches, 03_Lessons_Map, 06_Lists и Dashboard.
A13: Что изменено в v0.3.1 | B13: Добавлена колонка «Флагман урока (да/нет)» в 01_Master_Facts: по одному флагманскому узлу на каждый из PL-001–PL-006.
... A36: Следующий шаг | B36: PL-047: Недодержка — разобрать нехватку света, потерю деталей в тенях, отличие плёнки и цифры, экспокоррекцию и практику намеренной/случайной недодержки. PL-040 остаётся отдельным долгом в Модуле 4.
